Workbook

Sheet Resumen Ejecutivo
A1: RESUMEN EJECUTIVO — COSTO / BENEFICIO POR ÁREA (Año 2027)
A3: Área | B3: Inversión Anual | C3: Ingreso Anual | D3: Beneficio Neto | E3: ROI (%) | F3: ROI (x)
A4: LANZAMIENTO | B4: ='Reporte Costo-Beneficio'!AM6 -> 5000000 | C4: ='Reporte Costo-Beneficio'!AN6 -> 19025000 | D4: =C4-B4 -> 14025000 | E4: =IFERROR(D4/B4,"-") -> 2.805 | F4: =IFERROR(C4/B4,"-") -> 3.805
A5: PUBLICIDAD DIGITAL | B5: ='Reporte Costo-Beneficio'!AM9 -> 55100000 | C5: ='Reporte Costo-Beneficio'!AN9 -> 2.2139091e+08 | D5: =C5-B5 -> 1.6629091e+08 | E5: =IFERROR(D5/B5,"-") -> 3.0179838 | F5: =IFERROR(C5/B5,"-") -> 4.0179838
A6: DELIVERY Y FIDELIZACIÓN | B6: ='Reporte Costo-Beneficio'!AM17 -> 47800000 | C6: ='Reporte Costo-Beneficio'!AN17 -> 1.7661123e+08 | D6: =C6-B6 -> 1.2881123e+08 | E6: =IFERROR(D6/B6,"-") -> 2.6947955 | F6: =IFERROR(C6/B6,"-") -> 3.6947955
A7: FECHAS ESPECIALES | B7: ='Reporte Costo-Beneficio'!AM25 -> 20700000 | C7: ='Reporte Costo-Beneficio'!AN25 -> 90945000 | D7: =C7-B7 -> 70245000 | E7: =IFERROR(D7/B7,"-") -> 3.3934783 | F7: =IFERROR(C7/B7,"-") -> 4.3934783
A8: COMUNIDAD Y ALIANZAS | B8: ='Reporte Costo-Beneficio'!AM35 -> 10800000 | C8: ='Reporte Costo-Beneficio'!AN35 -> 29528750 | D8: =C8-B8 -> 18728750 | E8: =IFERROR(D8/B8,"-") -> 1.7341435 | F8: =IFERROR(C8/B8,"-") -> 2.7341435
A9: PRODUCTO Y MENÚ | B9: ='Reporte Costo-Beneficio'!AM41 -> 3000000 | C9: ='Reporte Costo-Beneficio'!AN41 -> 9000000 | D9: =C9-B9 -> 6000000 | E9: =IFERROR(D9/B9,"-") -> 2 | F9: =IFERROR(C9/B9,"-") -> 3
A10: TEMPORADA BAJA | B10: ='Reporte Costo-Beneficio'!AM43 -> 3300000 | C10: ='Reporte Costo-Beneficio'!AN43 -> 7099500 | D10: =C10-B10 -> 3799500 | E10: =IFERROR(D10/B10,"-") -> 1.1513636 | F10: =IFERROR(C10/B10,"-") -> 2.1513636
A11: TOTAL GENERAL | B11: =SUM(B4:B10) -> 145700000 | C11: =SUM(C4:C10) -> 5.5360039e+08 | D11: =SUM(D4:D10) -> 4.0790039e+08 | E11: =IFERROR(D11/B11,"-") -> 2.7995908 | F11: =IFERROR(C11/B11,"-") -> 3.7995908

Sheet Reporte Costo-Beneficio
A1: DÖNER HOUSE — PLAN DE COSTO / BENEFICIO DE MARKETING 2027 (FORECAST)
A2: Cifras en COP. Revenue = Investment x ROAS esperado x Índice de estacionalidad (ver hoja 'Supuestos'). ROI = (Revenue - Investment) / Investment.
A4: Área | B4: Canal | C4: Enero | F4: Febrero | I4: Marzo | L4: Abril | O4: Mayo | R4: Junio | U4: Julio | X4: Agosto | AA4: Septiembre | AD4: Octubre | AG4: Noviembre | AJ4: Diciembre | AM4: TOTAL ANUAL
C5: Forecast Investment | D5: Forecast Revenue | E5: ROI | F5: Forecast Investment | G5: Forecast Revenue | H5: ROI | I5: Forecast Investment | J5: Forecast Revenue | K5: ROI | L5: Forecast Investment | M5: Forecast Revenue | N5: ROI | O5: Forecast Investment | P5: Forecast Revenue | Q5: ROI | R5: Forecast Investment | S5: Forecast Revenue | T5: ROI | U5: Forecast Investment | V5: Forecast Revenue | W5: ROI | X5: Forecast Investment | Y5: Forecast Revenue | Z5: ROI | AA5: Forecast Investment | AB5: Forecast Revenue | AC5: ROI | AD5: Forecast Investment | AE5: Forecast Revenue | AF5: ROI | AG5: Forecast Investment | AH5: Forecast Revenue | AI5: ROI | AJ5: Forecast Investment | AK5: Forecast Revenue | AL5: ROI | AM5: Investment | AN5: Revenue | AO5: ROI
A6: LANZAMIENTO — Total | C6: =C7+C8 -> 4000000 | D6: =D7+D8 -> 15000000 | E6: =IFERROR((D6-C6)/C6,"-") -> 2.75 | F6: =F7+F8 -> 1000000 | G6: =G7+G8 -> 4025000 | H6: =IFERROR((G6-F6)/F6,"-") -> 3.025 | I6: =I7+I8 -> 0 | J6: =J7+J8 -> 0 | K6: =IFERROR((J6-I6)/I6,"-") -> - | L6: =L7+L8 -> 0 | M6: =M7+M8 -> 0 | N6: =IFERROR((M6-L6)/L6,"-") -> - | O6: =O7+O8 -> 0 | P6: =P7+P8 -> 0 | Q6: =IFERROR((P6-O6)/O6,"-") -> - | R6: =R7+R8 -> 0 | S6: =S7+S8 -> 0 | T6: =IFERROR((S6-R6)/R6,"-") -> - | U6: =U7+U8 -> 0 | V6: =V7+V8 -> 0 | W6: =IFERROR((V6-U6)/U6,"-") -> - | X6: =X7+X8 -> 0 | Y6: =Y7+Y8 -> 0 | Z6: =IFERROR((Y6-X6)/X6,"-") -> - | AA6: =AA7+AA8 -> 0 | AB6: =AB7+AB8 -> 0 | AC6: =IFERROR((AB6-AA6)/AA6,"-") -> - | AD6: =AD7+AD8 -> 0 | AE6: =AE7+AE8 -> 0 | AF6: =IFERROR((AE6-AD6)/AD6,"-") -> - | AG6: =AG7+AG8 -> 0 | AH6: =AH7+AH8 -> 0 | AI6: =IFERROR((AH6-AG6)/AG6,"-") -> - | AJ6: =AJ7+AJ8 -> 0 | AK6: =AK7+AK8 -> 0 | AL6: =IFERROR((AK6-AJ6)/AJ6,"-") -> - | AM6: =C6+F6+I6+L6+O6+R6+U6+X6+AA6+AD6+AG6+AJ6 -> 5000000 | AN6: =D6+G6+J6+M6+P6+S6+V6+Y6+AB6+AE6+AH6+AK6 -> 19025000 | AO6: =IFERROR((AN6-AM6)/AM6,"-") -> 2.805
A7: LANZAMIENTO | B7: Prensa y Redes (Teaser + PR + Promo apertura) | C7: =Supuestos!$C$12*Supuestos!$E$12/Supuestos!$Q$12 -> 3000000 | D7: =C7*Supuestos!$D$12*Supuestos!B$7 -> 10800000 | E7: =IFERROR((D7-C7)/C7,"-") -> 2.6 | F7: =Supuestos!$C$12*Supuestos!$F$12/Supuestos!$Q$12 -> 0 | G7: =F7*Supuestos!$D$12*Supuestos!C$7 -> 0 | H7: =IFERROR((G7-F7)/F7,"-") -> - | I7: =Supuestos!$C$12*Supuestos!$G$12/Supuestos!$Q$12 -> 0 | J7: =I7*Supuestos!$D$12*Supuestos!D$7 -> 0 | K7: =IFERROR((J7-I7)/I7,"-") -> - | L7: =Supuestos!$C$12*Supuestos!$H$12/Supuestos!$Q$12 -> 0 | M7: =L7*Supuestos!$D$12*Supuestos!E$7 -> 0 | N7: =IFERROR((M7-L7)/L7,"-") -> - | O7: =Supuestos!$C$12*Supuestos!$I$12/Supuestos!$Q$12 -> 0 | P7: =O7*Supuestos!$D$12*Supuestos!F$7 -> 0 | Q7: =IFERROR((P7-O7)/O7,"-") -> - | R7: =Supuestos!$C$12*Supuestos!$J$12/Supuestos!$Q$12 -> 0 | S7: =R7*Supuestos!$D$12*Supuestos!G$7 -> 0 | T7: =IFERROR((S7-R7)/R7,"-") -> - | U7: =Supuestos!$C$12*Supuestos!$K$12/Supuestos!$Q$12 -> 0 | V7: =U7*Supuestos!$D$12*Supuestos!H$7 -> 0 | W7: =IFERROR((V7-U7)/U7,"-") -> - | X7: =Supuestos!$C$12*Supuestos!$L$12/Supuestos!$Q$12 -> 0 | Y7: =X7*Supuestos!$D$12*Supuestos!I$7 -> 0 | Z7: =IFERROR((Y7-X7)/X7,"-") -> - | AA7: =Supuestos!$C$12*Supuestos!$M$12/Supuestos!$Q$12 -> 0 | AB7: =AA7*Supuestos!$D$12*Supuestos!J$7 -> 0 | AC7: =IFERROR((AB7-AA7)/AA7,"-") -> - | AD7: =Supuestos!$C$12*Supuestos!$N$12/Supuestos!$Q$12 -> 0 | AE7: =AD7*Supuestos!$D$12*Supuestos!K$7 -> 0 | AF7: =IFERROR((AE7-AD7)/AD7,"-") -> - | AG7: =Supuestos!$C$12*Supuestos!$O$12/Supuestos!$Q$12 -> 0 | AH7: =AG7*Supuestos!$D$12*Supuestos!L$7 -> 0 | AI7: =IFERROR((AH7-AG7)/AG7,"-") -> - | AJ7: =Supuestos!$C$12*Supuestos!$P$12/Supuestos!$Q$12 -> 0 | AK7: =AJ7*Supuestos!$D$12*Supuestos!M$7 -> 0 | AL7: =IFERROR((AK7-AJ7)/AJ7,"-") -> - | AM7: =C7+F7+I7+L7+O7+R7+U7+X7+AA7+AD7+AG7+AJ7 -> 3000000 | AN7: =D7+G7+J7+M7+P7+S7+V7+Y7+AB7+AE7+AH7+AK7 -> 10800000 | AO7: =IFERROR((AN7-AM7)/AM7,"-") -> 2.6
A8: LANZAMIENTO | B8: Volantes, degustaciones y garantía de satisfacción | C8: =Supuestos!$C$13*Supuestos!$E$13/Supuestos!$Q$13 -> 1000000 | D8: =C8*Supuestos!$D$13*Supuestos!B$7 -> 4200000 | E8: =IFERROR((D8-C8)/C8,"-") -> 3.2 | F8: =Supuestos!$C$13*Supuestos!$F$13/Supuestos!$Q$13 -> 1000000 | G8: =F8*Supuestos!$D$13*Supuestos!C$7 -> 4025000 | H8: =IFERROR((G8-F8)/F8,"-") -> 3.025 | I8: =Supuestos!$C$13*Supuestos!$G$13/Supuestos!$Q$13 -> 0 | J8: =I8*Supuestos!$D$13*Supuestos!D$7 -> 0 | K8: =IFERROR((J8-I8)/I8,"-") -> - | L8: =Supuestos!$C$13*Supuestos!$H$13/Supuestos!$Q$13 -> 0 | M8: =L8*Supuestos!$D$13*Supuestos!E$7 -> 0 | N8: =IFERROR((M8-L8)/L8,"-") -> - | O8: =Supuestos!$C$13*Supuestos!$I$13/Supuestos!$Q$13 -> 0 | P8: =O8*Supuestos!$D$13*Supuestos!F$7 -> 0 | Q8: =IFERROR((P8-O8)/O8,"-") -> - | R8: =Supuestos!$C$13*Supuestos!$J$13/Supuestos!$Q$13 -> 0 | S8: =R8*Supuestos!$D$13*Supuestos!G$7 -> 0 | T8: =IFERROR((S8-R8)/R8,"-") -> - | U8: =Supuestos!$C$13*Supuestos!$K$13/Supuestos!$Q$13 -> 0 | V8: =U8*Supuestos!$D$13*Supuestos!H$7 -> 0 | W8: =IFERROR((V8-U8)/U8,"-") -> - | X8: =Supuestos!$C$13*Supuestos!$L$13/Supuestos!$Q$13 -> 0 | Y8: =X8*Supuestos!$D$13*Supuestos!I$7 -> 0 | Z8: =IFERROR((Y8-X8)/X8,"-") -> - | AA8: =Supuestos!$C$13*Supuestos!$M$13/Supuestos!$Q$13 -> 0 | AB8: =AA8*Supuestos!$D$13*Supuestos!J$7 -> 0 | AC8: =IFERROR((AB8-AA8)/AA8,"-") -> - | AD8: =Supuestos!$C$13*Supuestos!$N$13/Supuestos!$Q$13 -> 0 | AE8: =AD8*Supuestos!$D$13*Supuestos!K$7 -> 0 | AF8: =IFERROR((AE8-AD8)/AD8,"-") -> - | AG8: =Supuestos!$C$13*Supuestos!$O$13/Supuestos!$Q$13 -> 0 | AH8: =AG8*Supuestos!$D$13*Supuestos!L$7 -> 0 | AI8: =IFERROR((AH8-AG8)/AG8,"-") -> - | AJ8: =Supuestos!$C$13*Supuestos!$P$13/Supuestos!$Q$13 -> 0 | AK8: =AJ8*Supuestos!$D$13*Supuestos!M$7 -> 0 | AL8: =IFERROR((AK8-AJ8)/AJ8,"-") -> - | AM8: =C8+F8+I8+L8+O8+R8+U8+X8+AA8+AD8+AG8+AJ8 -> 2000000 | AN8: =D8+G8+J8+M8+P8+S8+V8+Y8+AB8+AE8+AH8+AK8 -> 8225000 | AO8: =IFERROR((AN8-AM8)/AM8,"-") -> 3.1125
A9: PUBLICIDAD DIGITAL — Total | C9: =C10+C11+C12+C13+C14+C15+C16 -> 3100000 | D9: =D10+D11+D12+D13+D14+D15+D16 -> 13320000 | E9: =IFERROR((D9-C9)/C9,"-") -> 3.2967742 | F9: =F10+F11+F12+F13+F14+F15+F16 -> 7045454.5 | G9: =G10+G11+G12+G13+G14+G15+G16 -> 29115909 | H9: =IFERROR((G9-F9)/F9,"-") -> 3.1325806 | I9: =I10+I11+I12+I13+I14+I15+I16 -> 4045454.5 | J9: =J10+J11+J12+J13+J14+J15+J16 -> 14146364 | K9: =IFERROR((J9-I9)/I9,"-") -> 2.4968539 | L9: =L10+L11+L12+L13+L14+L15+L16 -> 4045454.5 | M9: =M10+M11+M12+M13+M14+M15+M16 -> 13360455 | N9: =IFERROR((M9-L9)/L9,"-") -> 2.3025843 | O9: =O10+O11+O12+O13+O14+O15+O16 -> 4045454.5 | P9: =P10+P11+P12+P13+P14+P15+P16 -> 16504091 | Q9: =IFERROR((P9-O9)/O9,"-") -> 3.0796629 | R9: =R10+R11+R12+R13+R14+R15+R16 -> 4045454.5 | S9: =S10+S11+S12+S13+S14+S15+S16 -> 14932273 | T9: =IFERROR((S9-R9)/R9,"-") -> 2.6911236 | U9: =U10+U11+U12+U13+U14+U15+U16 -> 4045454.5 | V9: =V10+V11+V12+V13+V14+V15+V16 -> 15718182 | W9: =IFERROR((V9-U9)/U9,"-") -> 2.8853933 | X9: =X10+X11+X12+X13+X14+X15+X16 -> 7045454.5 | Y9: =Y10+Y11+Y12+Y13+Y14+Y15+Y16 -> 26584091 | Z9: =IFERROR((Y9-X9)/X9,"-") -> 2.7732258 | AA9: =AA10+AA11+AA12+AA13+AA14+AA15+AA16 -> 4795454.5 | AB9: =AB10+AB11+AB12+AB13+AB14+AB15+AB16 -> 19600000 | AC9: =IFERROR((AB9-AA9)/AA9,"-") -> 3.0872038 | AD9: =AD10+AD11+AD12+AD13+AD14+AD15+AD16 -> 4795454.5 | AE9: =AE10+AE11+AE12+AE13+AE14+AE15+AE16 -> 19600000 | AF9: =IFERROR((AE9-AD9)/AD9,"-") -> 3.0872038 | AG9: =AG10+AG11+AG12+AG13+AG14+AG15+AG16 -> 4045454.5 | AH9: =AH10+AH11+AH12+AH13+AH14+AH15+AH16 -> 18075909 | AI9: =IFERROR((AH9-AG9)/AG9,"-") -> 3.4682022 | AJ9: =AJ10+AJ11+AJ12+AJ13+AJ14+AJ15+AJ16 -> 4045454.5 | AK9: =AK10+AK11+AK12+AK13+AK14+AK15+AK16 -> 20433636 | AL9: =IFERROR((AK9-AJ9)/AJ9,"-") -> 4.0510112 | AM9: =C9+F9+I9+L9+O9+R9+U9+X9+AA9+AD9+AG9+AJ9 -> 55100000 | AN9: =D9+G9+J9+M9+P9+S9+V9+Y9+AB9+AE9+AH9+AK9 -> 2.2139091e+08 | AO9: =IFERROR((AN9-AM9)/AM9,"-") -> 3.0179838
A10: PUBLICIDAD DIGITAL | B10: Contenido orgánico IG/TikTok/Facebook | C10: =Supuestos!$C$14*Supuestos!$E$14/Supuestos!$Q$14 -> 1000000 | D10: =C10*Supuestos!$D$14*Supuestos!B$7 -> 3000000 | E10: =IFERROR((D10-C10)/C10,"-") -> 2 | F10: =Supuestos!$C$14*Supuestos!$F$14/Supuestos!$Q$14 -> 1000000 | G10: =F10*Supuestos!$D$14*Supuestos!C$7 -> 2875000 | H10: =IFERROR((G10-F10)/F10,"-") -> 1.875 | I10: =Supuestos!$C$14*Supuestos!$G$14/Supuestos!$Q$14 -> 1000000 | J10: =I10*Supuestos!$D$14*Supuestos!D$7 -> 2250000 | K10: =IFERROR((J10-I10)/I10,"-") -> 1.25 | L10: =Supuestos!$C$14*Supuestos!$H$14/Supuestos!$Q$14 -> 1000000 | M10: =L10*Supuestos!$D$14*Supuestos!E$7 -> 2125000 | N10: =IFERROR((M10-L10)/L10,"-") -> 1.125 | O10: =Supuestos!$C$14*Supuestos!$I$14/Supuestos!$Q$14 -> 1000000 | P10: =O10*Supuestos!$D$14*Supuestos!F$7 -> 2625000 | Q10: =IFERROR((P10-O10)/O10,"-") -> 1.625 | R10: =Supuestos!$C$14*Supuestos!$J$14/Supuestos!$Q$14 -> 1000000 | S10: =R10*Supuestos!$D$14*Supuestos!G$7 -> 2375000 | T10: =IFERROR((S10-R10)/R10,"-") -> 1.375 | U10: =Supuestos!$C$14*Supuestos!$K$14/Supuestos!$Q$14 -> 1000000 | V10: =U10*Supuestos!$D$14*Supuestos!H$7 -> 2500000 | W10: =IFERROR((V10-U10)/U10,"-") -> 1.5 | X10: =Supuestos!$C$14*Supuestos!$L$14/Supuestos!$Q$14 -> 1000000 | Y10: =X10*Supuestos!$D$14*Supuestos!I$7 -> 2625000 | Z10: =IFERROR((Y10-X10)/X10,"-") -> 1.625 | AA10: =Supuestos!$C$14*Supuestos!$M$14/Supuestos!$Q$14 -> 1000000 | AB10: =AA10*Supuestos!$D$14*Supuestos!J$7 -> 2750000 | AC10: =IFERROR((AB10-AA10)/AA10,"-") -> 1.75 | AD10: =Supuestos!$C$14*Supuestos!$N$14/Supuestos!$Q$14 -> 1000000 | AE10: =AD10*Supuestos!$D$14*Supuestos!K$7 -> 2750000 | AF10: =IFERROR((AE10-AD10)/AD10,"-") -> 1.75 | AG10: =Supuestos!$C$14*Supuestos!$O$14/Supuestos!$Q$14 -> 1000000 | AH10: =AG10*Supuestos!$D$14*Supuestos!L$7 -> 2875000 | AI10: =IFERROR((AH10-AG10)/AG10,"-") -> 1.875 | AJ10: =Supuestos!$C$14*Supuestos!$P$14/Supuestos!$Q$14 -> 1000000 | AK10: =AJ10*Supuestos!$D$14*Supuestos!M$7 -> 3250000 | AL10: =IFERROR((AK10-AJ10)/AJ10,"-") -> 2.25 | AM10: =C10+F10+I10+L10+O10+R10+U10+X10+AA10+AD10+AG10+AJ10 -> 12000000 | AN10: =D10+G10+J10+M10+P10+S10+V10+Y10+AB10+AE10+AH10+AK10 -> 32000000 | AO10: =IFERROR((AN10-AM10)/AM10,"-") -> 1.6666667
A11: PUBLICIDAD DIGITAL | B11: Google Business Profile (SEO local) | C11: =Supuestos!$C$15*Supuestos!$E$15/Supuestos!$Q$15 -> 100000 | D11: =C11*Supuestos!$D$15*Supuestos!B$7 -> 720000 | E11: =IFERROR((D11-C11)/C11,"-") -> 6.2 | F11: =Supuestos!$C$15*Supuestos!$F$15/Supuestos!$Q$15 -> 100000 | G11: =F11*Supuestos!$D$15*Supuestos!C$7 -> 690000 | H11: =IFERROR((G11-F11)/F11,"-") -> 5.9 | I11: =Supuestos!$C$15*Supuestos!$G$15/Supuestos!$Q$15 -> 100000 | J11: =I11*Supuestos!$D$15*Supuestos!D$7 -> 540000 | K11: =IFERROR((J11-I11)/I11,"-") -> 4.4 | L11: =Supuestos!$C$15*Supuestos!$H$15/Supuestos!$Q$15 -> 100000 | M11: =L11*Supuestos!$D$15*Supuestos!E$7 -> 510000 | N11: =IFERROR((M11-L11)/L11,"-") -> 4.1 | O11: =Supuestos!$C$15*Supuestos!$I$15/Supuestos!$Q$15 -> 100000 | P11: =O11*Supuestos!$D$15*Supuestos!F$7 -> 630000 | Q11: =IFERROR((P11-O11)/O11,"-") -> 5.3 | R11: =Supuestos!$C$15*Supuestos!$J$15/Supuestos!$Q$15 -> 100000 | S11: =R11*Supuestos!$D$15*Supuestos!G$7 -> 570000 | T11: =IFERROR((S11-R11)/R11,"-") -> 4.7 | U11: =Supuestos!$C$15*Supuestos!$K$15/Supuestos!$Q$15 -> 100000 | V11: =U11*Supuestos!$D$15*Supuestos!H$7 -> 600000 | W11: =IFERROR((V11-U11)/U11,"-") -> 5 | X11: =Supuestos!$C$15*Supuestos!$L$15/Supuestos!$Q$15 -> 100000 | Y11: =X11*Supuestos!$D$15*Supuestos!I$7 -> 630000 | Z11: =IFERROR((Y11-X11)/X11,"-") -> 5.3 | AA11: =Supuestos!$C$15*Supuestos!$M$15/Supuestos!$Q$15 -> 100000 | AB11: =AA11*Supuestos!$D$15*Supuestos!J$7 -> 660000 | AC11: =IFERROR((AB11-AA11)/AA11,"-") -> 5.6 | AD11: =Supuestos!$C$15*Supuestos!$N$15/Supuestos!$Q$15 -> 100000 | AE11: =AD11*Supuestos!$D$15*Supuestos!K$7 -> 660000 | AF11: =IFERROR((AE11-AD11)/AD11,"-") -> 5.6 | AG11: =Supuestos!$C$15*Supuestos!$O$15/Supuestos!$Q$15 -> 100000 | AH11: =AG11*Supuestos!$D$15*Supuestos!L$7 -> 690000 | AI11: =IFERROR((AH11-AG11)/AG11,"-") -> 5.9 | AJ11: =Supuestos!$C$15*Supuestos!$P$15/Supuestos!$Q$15 -> 100000 | AK11: =AJ11*Supuestos!$D$15*Supuestos!M$7 -> 780000 | AL11: =IFERROR((AK11-AJ11)/AJ11,"-") -> 6.8 | AM11: =C11+F11+I11+L11+O11+R11+U11+X11+AA11+AD11+AG11+AJ11 -> 1200000 | AN11: =D11+G11+J11+M11+P11+S11+V11+Y11+AB11+AE11+AH11+AK11 -> 7680000 | AO11: =IFERROR((AN11-AM11)/AM11,"-") -> 5.4
A12: PUBLICIDAD DIGITAL | B12: Meta Ads pagado (geo-segmentado) | C12: =Supuestos!$C$16*Supuestos!$E$16/Supuestos!$Q$16 -> 2000000 | D12: =C12*Supuestos!$D$16*Supuestos!B$7 -> 9600000 | E12: =IFERROR((D12-C12)/C12,"-") -> 3.8 | F12: =Supuestos!$C$16*Supuestos!$F$16/Supuestos!$Q$16 -> 2000000 | G12: =F12*Supuestos!$D$16*Supuestos!C$7 -> 9200000 | H12: =IFERROR((G12-F12)/F12,"-") -> 3.6 | I12: =Supuestos!$C$16*Supuestos!$G$16/Supuestos!$Q$16 -> 2000000 | J12: =I12*Supuestos!$D$16*Supuestos!D$7 -> 7200000 | K12: =IFERROR((J12-I12)/I12,"-") -> 2.6 | L12: =Supuestos!$C$16*Supuestos!$H$16/Supuestos!$Q$16 -> 2000000 | M12: =L12*Supuestos!$D$16*Supuestos!E$7 -> 6800000 | N12: =IFERROR((M12-L12)/L12,"-") -> 2.4 | O12: =Supuestos!$C$16*Supuestos!$I$16/Supuestos!$Q$16 -> 2000000 | P12: =O12*Supuestos!$D$16*Supuestos!F$7 -> 8400000 | Q12: =IFERROR((P12-O12)/O12,"-") -> 3.2 | R12: =Supuestos!$C$16*Supuestos!$J$16/Supuestos!$Q$16 -> 2000000 | S12: =R12*Supuestos!$D$16*Supuestos!G$7 -> 7600000 | T12: =IFERROR((S12-R12)/R12,"-") -> 2.8 | U12: =Supuestos!$C$16*Supuestos!$K$16/Supuestos!$Q$16 -> 2000000 | V12: =U12*Supuestos!$D$16*Supuestos!H$7 -> 8000000 | W12: =IFERROR((V12-U12)/U12,"-") -> 3 | X12: =Supuestos!$C$16*Supuestos!$L$16/Supuestos!$Q$16 -> 2000000 | Y12: =X12*Supuestos!$D$16*Supuestos!I$7 -> 8400000 | Z12: =IFERROR((Y12-X12)/X12,"-") -> 3.2 | AA12: =Supuestos!$C$16*Supuestos!$M$16/Supuestos!$Q$16 -> 2000000 | AB12: =AA12*Supuestos!$D$16*Supuestos!J$7 -> 8800000 | AC12: =IFERROR((AB12-AA12)/AA12,"-") -> 3.4 | AD12: =Supuestos!$C$16*Supuestos!$N$16/Supuestos!$Q$16 -> 2000000 | AE12: =AD12*Supuestos!$D$16*Supuestos!K$7 -> 8800000 | AF12: =IFERROR((AE12-AD12)/AD12,"-") -> 3.4 | AG12: =Supuestos!$C$16*Supuestos!$O$16/Supuestos!$Q$16 -> 2000000 | AH12: =AG12*Supuestos!$D$16*Supuestos!L$7 -> 9200000 | AI12: =IFERROR((AH12-AG12)/AG12,"-") -> 3.6 | AJ12: =Supuestos!$C$16*Supuestos!$P$16/Supuestos!$Q$16 -> 2000000 | AK12: =AJ12*Supuestos!$D$16*Supuestos!M$7 -> 10400000 | AL12: =IFERROR((AK12-AJ12)/AJ12,"-") -> 4.2 | AM12: =C12+F12+I12+L12+O12+R12+U12+X12+AA12+AD12+AG12+AJ12 -> 24000000 | AN12: =D12+G12+J12+M12+P12+S12+V12+Y12+AB12+AE12+AH12+AK12 -> 102400000 | AO12: =IFERROR((AN12-AM12)/AM12,"-") -> 3.2666667
A13: PUBLICIDAD DIGITAL | B13: Influencers y bloggers gastronómicos | C13: =Supuestos!$C$17*Supuestos!$E$17/Supuestos!$Q$17 -> 0 | D13: =C13*Supuestos!$D$17*Supuestos!B$7 -> 0 | E13: =IFERROR((D13-C13)/C13,"-") -> - | F13: =Supuestos!$C$17*Supuestos!$F$17/Supuestos!$Q$17 -> 3000000 | G13: =F13*Supuestos!$D$17*Supuestos!C$7 -> 11040000 | H13: =IFERROR((G13-F13)/F13,"-") -> 2.68 | I13: =Supuestos!$C$17*Supuestos!$G$17/Supuestos!$Q$17 -> 0 | J13: =I13*Supuestos!$D$17*Supuestos!D$7 -> 0 | K13: =IFERROR((J13-I13)/I13,"-") -> - | L13: =Supuestos!$C$17*Supuestos!$H$17/Supuestos!$Q$17 -> 0 | M13: =L13*Supuestos!$D$17*Supuestos!E$7 -> 0 | N13: =IFERROR((M13-L13)/L13,"-") -> - | O13: =Supuestos!$C$17*Supuestos!$I$17/Supuestos!$Q$17 -> 0 | P13: =O13*Supuestos!$D$17*Supuestos!F$7 -> 0 | Q13: =IFERROR((P13-O13)/O13,"-") -> - | R13: =Supuestos!$C$17*Supuestos!$J$17/Supuestos!$Q$17 -> 0 | S13: =R13*Supuestos!$D$17*Supuestos!G$7 -> 0 | T13: =IFERROR((S13-R13)/R13,"-") -> - | U13: =Supuestos!$C$17*Supuestos!$K$17/Supuestos!$Q$17 -> 0 | V13: =U13*Supuestos!$D$17*Supuestos!H$7 -> 0 | W13: =IFERROR((V13-U13)/U13,"-") -> - | X13: =Supuestos!$C$17*Supuestos!$L$17/Supuestos!$Q$17 -> 3000000 | Y13: =X13*Supuestos!$D$17*Supuestos!I$7 -> 10080000 | Z13: =IFERROR((Y13-X13)/X13,"-") -> 2.36 | AA13: =Supuestos!$C$17*Supuestos!$M$17/Supuestos!$Q$17 -> 0 | AB13: =AA13*Supuestos!$D$17*Supuestos!J$7 -> 0 | AC13: =IFERROR((AB13-AA13)/AA13,"-") -> - | AD13: =Supuestos!$C$17*Supuestos!$N$17/Supuestos!$Q$17 -> 0 | AE13: =AD13*Supuestos!$D$17*Supuestos!K$7 -> 0 | AF13: =IFERROR((AE13-AD13)/AD13,"-") -> - | AG13: =Supuestos!$C$17*Supuestos!$O$17/Supuestos!$Q$17 -> 0 | AH13: =AG13*Supuestos!$D$17*Supuestos!L$7 -> 0 | AI13: =IFERROR((AH13-AG13)/AG13,"-") -> - | AJ13: =Supuestos!$C$17*Supuestos!$P$17/Supuestos!$Q$17 -> 0 | AK13: =AJ13*Supuestos!$D$17*Supuestos!M$7 -> 0 | AL13: =IFERROR((AK13-AJ13)/AJ13,"-") -> - | AM13: =C13+F13+I13+L13+O13+R13+U13+X13+AA13+AD13+AG13+AJ13 -> 6000000 | AN13: =D13+G13+J13+M13+P13+S13+V13+Y13+AB13+AE13+AH13+AK13 -> 21120000 | AO13: =IFERROR((AN13-AM13)/AM13,"-") -> 2.52
A14: PUBLICIDAD DIGITAL | B14: QR en empaques/recibos + referidos | C14: =Supuestos!$C$18*Supuestos!$E$18/Supuestos!$Q$18 -> 0 | D14: =C14*Supuestos!$D$18*Supuestos!B$7 -> 0 | E14: =IFERROR((D14-C14)/C14,"-") -> - | F14: =Supuestos!$C$18*Supuestos!$F$18/Supuestos!$Q$18 -> 727272.73 | G14: =F14*Supuestos!$D$18*Supuestos!C$7 -> 4181818.2 | H14: =IFERROR((G14-F14)/F14,"-") -> 4.75 | I14: =Supuestos!$C$18*Supuestos!$G$18/Supuestos!$Q$18 -> 727272.73 | J14: =I14*Supuestos!$D$18*Supuestos!D$7 -> 3272727.3 | K14: =IFERROR((J14-I14)/I14,"-") -> 3.5 | L14: =Supuestos!$C$18*Supuestos!$H$18/Supuestos!$Q$18 -> 727272.73 | M14: =L14*Supuestos!$D$18*Supuestos!E$7 -> 3090909.1 | N14: =IFERROR((M14-L14)/L14,"-") -> 3.25 | O14: =Supuestos!$C$18*Supuestos!$I$18/Supuestos!$Q$18 -> 727272.73 | P14: =O14*Supuestos!$D$18*Supuestos!F$7 -> 3818181.8 | Q14: =IFERROR((P14-O14)/O14,"-") -> 4.25 | R14: =Supuestos!$C$18*Supuestos!$J$18/Supuestos!$Q$18 -> 727272.73 | S14: =R14*Supuestos!$D$18*Supuestos!G$7 -> 3454545.5 | T14: =IFERROR((S14-R14)/R14,"-") -> 3.75 | U14: =Supuestos!$C$18*Supuestos!$K$18/Supuestos!$Q$18 -> 727272.73 | V14: =U14*Supuestos!$D$18*Supuestos!H$7 -> 3636363.6 | W14: =IFERROR((V14-U14)/U14,"-") -> 4 | X14: =Supuestos!$C$18*Supuestos!$L$18/Supuestos!$Q$18 -> 727272.73 | Y14: =X14*Supuestos!$D$18*Supuestos!I$7 -> 3818181.8 | Z14: =IFERROR((Y14-X14)/X14,"-") -> 4.25 | AA14: =Supuestos!$C$18*Supuestos!$M$18/Supuestos!$Q$18 -> 727272.73 | AB14: =AA14*Supuestos!$D$18*Supuestos!J$7 -> 4000000 | AC14: =IFERROR((AB14-AA14)/AA14,"-") -> 4.5 | AD14: =Supuestos!$C$18*Supuestos!$N$18/Supuestos!$Q$18 -> 727272.73 | AE14: =AD14*Supuestos!$D$18*Supuestos!K$7 -> 4000000 | AF14: =IFERROR((AE14-AD14)/AD14,"-") -> 4.5 | AG14: =Supuestos!$C$18*Supuestos!$O$18/Supuestos!$Q$18 -> 727272.73 | AH14: =AG14*Supuestos!$D$18*Supuestos!L$7 -> 4181818.2 | AI14: =IFERROR((AH14-AG14)/AG14,"-") -> 4.75 | AJ14: =Supuestos!$C$18*Supuestos!$P$18/Supuestos!$Q$18 -> 727272.73 | AK14: =AJ14*Supuestos!$D$18*Supuestos!M$7 -> 4727272.7 | AL14: =IFERROR((AK14-AJ14)/AJ14,"-") -> 5.5 | AM14: =C14+F14+I14+L14+O14+R14+U14+X14+AA14+AD14+AG14+AJ14 -> 8000000 | AN14: =D14+G14+J14+M14+P14+S14+V14+Y14+AB14+AE14+AH14+AK14 -> 42181818 | AO14: =IFERROR((AN14-AM14)/AM14,"-") -> 4.2727273
A15: PUBLICIDAD DIGITAL | B15: WhatsApp Business (catálogo + broadcast) | C15: =Supuestos!$C$19*Supuestos!$E$19/Supuestos!$Q$19 -> 0 | D15: =C15*Supuestos!$D$19*Supuestos!B$7 -> 0 | E15: =IFERROR((D15-C15)/C15,"-") -> - | F15: =Supuestos!$C$19*Supuestos!$F$19/Supuestos!$Q$19 -> 218181.82 | G15: =F15*Supuestos!$D$19*Supuestos!C$7 -> 1129090.9 | H15: =IFERROR((G15-F15)/F15,"-") -> 4.175 | I15: =Supuestos!$C$19*Supuestos!$G$19/Supuestos!$Q$19 -> 218181.82 | J15: =I15*Supuestos!$D$19*Supuestos!D$7 -> 883636.36 | K15: =IFERROR((J15-I15)/I15,"-") -> 3.05 | L15: =Supuestos!$C$19*Supuestos!$H$19/Supuestos!$Q$19 -> 218181.82 | M15: =L15*Supuestos!$D$19*Supuestos!E$7 -> 834545.45 | N15: =IFERROR((M15-L15)/L15,"-") -> 2.825 | O15: =Supuestos!$C$19*Supuestos!$I$19/Supuestos!$Q$19 -> 218181.82 | P15: =O15*Supuestos!$D$19*Supuestos!F$7 -> 1030909.1 | Q15: =IFERROR((P15-O15)/O15,"-") -> 3.725 | R15: =Supuestos!$C$19*Supuestos!$J$19/Supuestos!$Q$19 -> 218181.82 | S15: =R15*Supuestos!$D$19*Supuestos!G$7 -> 932727.27 | T15: =IFERROR((S15-R15)/R15,"-") -> 3.275 | U15: =Supuestos!$C$19*Supuestos!$K$19/Supuestos!$Q$19 -> 218181.82 | V15: =U15*Supuestos!$D$19*Supuestos!H$7 -> 981818.18 | W15: =IFERROR((V15-U15)/U15,"-") -> 3.5 | X15: =Supuestos!$C$19*Supuestos!$L$19/Supuestos!$Q$19 -> 218181.82 | Y15: =X15*Supuestos!$D$19*Supuestos!I$7 -> 1030909.1 | Z15: =IFERROR((Y15-X15)/X15,"-") -> 3.725 | AA15: =Supuestos!$C$19*Supuestos!$M$19/Supuestos!$Q$19 -> 218181.82 | AB15: =AA15*Supuestos!$D$19*Supuestos!J$7 -> 1080000 | AC15: =IFERROR((AB15-AA15)/AA15,"-") -> 3.95 | AD15: =Supuestos!$C$19*Supuestos!$N$19/Supuestos!$Q$19 -> 218181.82 | AE15: =AD15*Supuestos!$D$19*Supuestos!K$7 -> 1080000 | AF15: =IFERROR((AE15-AD15)/AD15,"-") -> 3.95 | AG15: =Supuestos!$C$19*Supuestos!$O$19/Supuestos!$Q$19 -> 218181.82 | AH15: =AG15*Supuestos!$D$19*Supuestos!L$7 -> 1129090.9 | AI15: =IFERROR((AH15-AG15)/AG15,"-") -> 4.175 | AJ15: =Supuestos!$C$19*Supuestos!$P$19/Supuestos!$Q$19 -> 218181.82 | AK15: =AJ15*Supuestos!$D$19*Supuestos!M$7 -> 1276363.6 | AL15: =IFERROR((AK15-AJ15)/AJ15,"-") -> 4.85 | AM15: =C15+F15+I15+L15+O15+R15+U15+X15+AA15+AD15+AG15+AJ15 -> 2400000 | AN15: =D15+G15+J15+M15+P15+S15+V15+Y15+AB15+AE15+AH15+AK15 -> 11389091 | AO15: =IFERROR((AN15-AM15)/AM15,"-") -> 3.7454545
A16: PUBLICIDAD DIGITAL | B16: Reto TikTok "el wrap perfecto" | C16: =Supuestos!$C$20*Supuestos!$E$20/Supuestos!$Q$20 -> 0 | D16: =C16*Supuestos!$D$20*Supuestos!B$7 -> 0 | E16: =IFERROR((D16-C16)/C16,"-") -> - | F16: =Supuestos!$C$20*Supuestos!$F$20/Supuestos!$Q$20 -> 0 | G16: =F16*Supuestos!$D$20*Supuestos!C$7 -> 0 | H16: =IFERROR((G16-F16)/F16,"-") -> - | I16: =Supuestos!$C$20*Supuestos!$G$20/Supuestos!$Q$20 -> 0 | J16: =I16*Supuestos!$D$20*Supuestos!D$7 -> 0 | K16: =IFERROR((J16-I16)/I16,"-") -> - | L16: =Supuestos!$C$20*Supuestos!$H$20/Supuestos!$Q$20 -> 0 | M16: =L16*Supuestos!$D$20*Supuestos!E$7 -> 0 | N16: =IFERROR((M16-L16)/L16,"-") -> - | O16: =Supuestos!$C$20*Supuestos!$I$20/Supuestos!$Q$20 -> 0 | P16: =O16*Supuestos!$D$20*Supuestos!F$7 -> 0 | Q16: =IFERROR((P16-O16)/O16,"-") -> - | R16: =Supuestos!$C$20*Supuestos!$J$20/Supuestos!$Q$20 -> 0 | S16: =R16*Supuestos!$D$20*Supuestos!G$7 -> 0 | T16: =IFERROR((S16-R16)/R16,"-") -> - | U16: =Supuestos!$C$20*Supuestos!$K$20/Supuestos!$Q$20 -> 0 | V16: =U16*Supuestos!$D$20*Supuestos!H$7 -> 0 | W16: =IFERROR((V16-U16)/U16,"-") -> - | X16: =Supuestos!$C$20*Supuestos!$L$20/Supuestos!$Q$20 -> 0 | Y16: =X16*Supuestos!$D$20*Supuestos!I$7 -> 0 | Z16: =IFERROR((Y16-X16)/X16,"-") -> - | AA16: =Supuestos!$C$20*Supuestos!$M$20/Supuestos!$Q$20 -> 750000 | AB16: =AA16*Supuestos!$D$20*Supuestos!J$7 -> 2310000 | AC16: =IFERROR((AB16-AA16)/AA16,"-") -> 2.08 | AD16: =Supuestos!$C$20*Supuestos!$N$20/Supuestos!$Q$20 -> 750000 | AE16: =AD16*Supuestos!$D$20*Supuestos!K$7 -> 2310000 | AF16: =IFERROR((AE16-AD16)/AD16,"-") -> 2.08 | AG16: =Supuestos!$C$20*Supuestos!$O$20/Supuestos!$Q$20 -> 0 | AH16: =AG16*Supuestos!$D$20*Supuestos!L$7 -> 0 | AI16: =IFERROR((AH16-AG16)/AG16,"-") -> - | AJ16: =Supuestos!$C$20*Supuestos!$P$20/Supuestos!$Q$20 -> 0 | AK16: =AJ16*Supuestos!$D$20*Supuestos!M$7 -> 0 | AL16: =IFERROR((AK16-AJ16)/AJ16,"-") -> - | AM16: =C16+F16+I16+L16+O16+R16+U16+X16+AA16+AD16+AG16+AJ16 -> 1500000 | AN16: =D16+G16+J16+M16+P16+S16+V16+Y16+AB16+AE16+AH16+AK16 -> 4620000 | AO16: =IFERROR((AN16-AM16)/AM16,"-") -> 2.08
A17: DELIVERY Y FIDELIZACIÓN — Total | C17: =C18+C19+C20+C21+C22+C23+C24 -> 3000000 | D17: =D18+D19+D20+D21+D22+D23+D24 -> 9000000 | E17: =IFERROR((D17-C17)/C17,"-") -> 2 | F17: =F18+F19+F20+F21+F22+F23+F24 -> 5613636.4 | G17: =G18+G19+G20+G21+G22+G23+G24 -> 19210227 | H17: =IFERROR((G17-F17)/F17,"-") -> 2.4220648 | I17: =I18+I19+I20+I21+I22+I23+I24 -> 3913636.4 | J17: =J18+J19+J20+J21+J22+J23+J24 -> 12631091 | K17: =IFERROR((J17-I17)/I17,"-") -> 2.2274564 | L17: =L18+L19+L20+L21+L22+L23+L24 -> 4413636.4 | M17: =M18+M19+M20+M21+M22+M23+M24 -> 13841864 | N17: =IFERROR((M17-L17)/L17,"-") -> 2.1361586 | O17: =O18+O19+O20+O21+O22+O23+O24 -> 4413636.4 | P17: =P18+P19+P20+P21+P22+P23+P24 -> 17098773 | Q17: =IFERROR((P17-O17)/O17,"-") -> 2.8740783 | R17: =R18+R19+R20+R21+R22+R23+R24 -> 3163636.4 | S17: =S18+S19+S20+S21+S22+S23+S24 -> 11907818 | T17: =IFERROR((S17-R17)/R17,"-") -> 2.7639655 | U17: =U18+U19+U20+U21+U22+U23+U24 -> 3163636.4 | V17: =V18+V19+V20+V21+V22+V23+V24 -> 12534545 | W17: =IFERROR((V17-U17)/U17,"-") -> 2.962069 | X17: =X18+X19+X20+X21+X22+X23+X24 -> 3913636.4 | Y17: =Y18+Y19+Y20+Y21+Y22+Y23+Y24 -> 14736273 | Z17: =IFERROR((Y17-X17)/X17,"-") -> 2.7653659 | AA17: =AA18+AA19+AA20+AA21+AA22+AA23+AA24 -> 3913636.4 | AB17: =AB18+AB19+AB20+AB21+AB22+AB23+AB24 -> 15438000 | AC17: =IFERROR((AB17-AA17)/AA17,"-") -> 2.944669 | AD17: =AD18+AD19+AD20+AD21+AD22+AD23+AD24 -> 4813636.4 | AE17: =AE18+AE19+AE20+AE21+AE22+AE23+AE24 -> 18012000 | AF17: =IFERROR((AE17-AD17)/AD17,"-") -> 2.7418697 | AG17: =AG18+AG19+AG20+AG21+AG22+AG23+AG24 -> 4813636.4 | AH17: =AH18+AH19+AH20+AH21+AH22+AH23+AH24 -> 18830727 | AI17: =IFERROR((AH17-AG17)/AG17,"-") -> 2.9119547 | AJ17: =AJ18+AJ19+AJ20+AJ21+AJ22+AJ23+AJ24 -> 2663636.4 | AK17: =AK18+AK19+AK20+AK21+AK22+AK23+AK24 -> 13369909 | AL17: =IFERROR((AK17-AJ17)/AJ17,"-") -> 4.0194198 | AM17: =C17+F17+I17+L17+O17+R17+U17+X17+AA17+AD17+AG17+AJ17 -> 47800000 | AN17: =D17+G17+J17+M17+P17+S17+V17+Y17+AB17+AE17+AH17+AK17 -> 1.7661123e+08 | AO17: =IFERROR((AN17-AM17)/AM17,"-") -> 2.6947955
A18: DELIVERY Y FIDELIZACIÓN | B18: Lanzamiento apps delivery (dcto. introductorio) | C18: =Supuestos!$C$21*Supuestos!$E$21/Supuestos!$Q$21 -> 3000000 | D18: =C18*Supuestos!$D$21*Supuestos!B$7 -> 9000000 | E18: =IFERROR((D18-C18)/C18,"-") -> 2 | F18: =Supuestos!$C$21*Supuestos!$F$21/Supuestos!$Q$21 -> 3000000 | G18: =F18*Supuestos!$D$21*Supuestos!C$7 -> 8625000 | H18: =IFERROR((G18-F18)/F18,"-") -> 1.875 | I18: =Supuestos!$C$21*Supuestos!$G$21/Supuestos!$Q$21 -> 0 | J18: =I18*Supuestos!$D$21*Supuestos!D$7 -> 0 | K18: =IFERROR((J18-I18)/I18,"-") -> - | L18: =Supuestos!$C$21*Supuestos!$H$21/Supuestos!$Q$21 -> 0 | M18: =L18*Supuestos!$D$21*Supuestos!E$7 -> 0 | N18: =IFERROR((M18-L18)/L18,"-") -> - | O18: =Supuestos!$C$21*Supuestos!$I$21/Supuestos!$Q$21 -> 0 | P18: =O18*Supuestos!$D$21*Supuestos!F$7 -> 0 | Q18: =IFERROR((P18-O18)/O18,"-") -> - | R18: =Supuestos!$C$21*Supuestos!$J$21/Supuestos!$Q$21 -> 0 | S18: =R18*Supuestos!$D$21*Supuestos!G$7 -> 0 | T18: =IFERROR((S18-R18)/R18,"-") -> - | U18: =Supuestos!$C$21*Supuestos!$K$21/Supuestos!$Q$21 -> 0 | V18: =U18*Supuestos!$D$21*Supuestos!H$7 -> 0 | W18: =IFERROR((V18-U18)/U18,"-") -> - | X18: =Supuestos!$C$21*Supuestos!$L$21/Supuestos!$Q$21 -> 0 | Y18: =X18*Supuestos!$D$21*Supuestos!I$7 -> 0 | Z18: =IFERROR((Y18-X18)/X18,"-") -> - | AA18: =Supuestos!$C$21*Supuestos!$M$21/Supuestos!$Q$21 -> 0 | AB18: =AA18*Supuestos!$D$21*Supuestos!J$7 -> 0 | AC18: =IFERROR((AB18-AA18)/AA18,"-") -> - | AD18: =Supuestos!$C$21*Supuestos!$N$21/Supuestos!$Q$21 -> 0 | AE18: =AD18*Supuestos!$D$21*Supuestos!K$7 -> 0 | AF18: =IFERROR((AE18-AD18)/AD18,"-") -> - | AG18: =Supuestos!$C$21*Supuestos!$O$21/Supuestos!$Q$21 -> 0 | AH18: =AG18*Supuestos!$D$21*Supuestos!L$7 -> 0 | AI18: =IFERROR((AH18-AG18)/AG18,"-") -> - | AJ18: =Supuestos!$C$21*Supuestos!$P$21/Supuestos!$Q$21 -> 0 | AK18: =AJ18*Supuestos!$D$21*Supuestos!M$7 -> 0 | AL18: =IFERROR((AK18-AJ18)/AJ18,"-") -> - | AM18: =C18+F18+I18+L18+O18+R18+U18+X18+AA18+AD18+AG18+AJ18 -> 6000000 | AN18: =D18+G18+J18+M18+P18+S18+V18+Y18+AB18+AE18+AH18+AK18 -> 17625000 | AO18: =IFERROR((AN18-AM18)/AM18,"-") -> 1.9375
A19: DELIVERY Y FIDELIZACIÓN | B19: Tarjeta de lealtad (10º döner gratis) | C19: =Supuestos!$C$22*Supuestos!$E$22/Supuestos!$Q$22 -> 0 | D19: =C19*Supuestos!$D$22*Supuestos!B$7 -> 0 | E19: =IFERROR((D19-C19)/C19,"-") -> - | F19: =Supuestos!$C$22*Supuestos!$F$22/Supuestos!$Q$22 -> 1363636.4 | G19: =F19*Supuestos!$D$22*Supuestos!C$7 -> 6272727.3 | H19: =IFERROR((G19-F19)/F19,"-") -> 3.6 | I19: =Supuestos!$C$22*Supuestos!$G$22/Supuestos!$Q$22 -> 1363636.4 | J19: =I19*Supuestos!$D$22*Supuestos!D$7 -> 4909090.9 | K19: =IFERROR((J19-I19)/I19,"-") -> 2.6 | L19: =Supuestos!$C$22*Supuestos!$H$22/Supuestos!$Q$22 -> 1363636.4 | M19: =L19*Supuestos!$D$22*Supuestos!E$7 -> 4636363.6 | N19: =IFERROR((M19-L19)/L19,"-") -> 2.4 | O19: =Supuestos!$C$22*Supuestos!$I$22/Supuestos!$Q$22 -> 1363636.4 | P19: =O19*Supuestos!$D$22*Supuestos!F$7 -> 5727272.7 | Q19: =IFERROR((P19-O19)/O19,"-") -> 3.2 | R19: =Supuestos!$C$22*Supuestos!$J$22/Supuestos!$Q$22 -> 1363636.4 | S19: =R19*Supuestos!$D$22*Supuestos!G$7 -> 5181818.2 | T19: =IFERROR((S19-R19)/R19,"-") -> 2.8 | U19: =Supuestos!$C$22*Supuestos!$K$22/Supuestos!$Q$22 -> 1363636.4 | V19: =U19*Supuestos!$D$22*Supuestos!H$7 -> 5454545.5 | W19: =IFERROR((V19-U19)/U19,"-") -> 3 | X19: =Supuestos!$C$22*Supuestos!$L$22/Supuestos!$Q$22 -> 1363636.4 | Y19: =X19*Supuestos!$D$22*Supuestos!I$7 -> 5727272.7 | Z19: =IFERROR((Y19-X19)/X19,"-") -> 3.2 | AA19: =Supuestos!$C$22*Supuestos!$M$22/Supuestos!$Q$22 -> 1363636.4 | AB19: =AA19*Supuestos!$D$22*Supuestos!J$7 -> 6000000 | AC19: =IFERROR((AB19-AA19)/AA19,"-") -> 3.4 | AD19: =Supuestos!$C$22*Supuestos!$N$22/Supuestos!$Q$22 -> 1363636.4 | AE19: =AD19*Supuestos!$D$22*Supuestos!K$7 -> 6000000 | AF19: =IFERROR((AE19-AD19)/AD19,"-") -> 3.4 | AG19: =Supuestos!$C$22*Supuestos!$O$22/Supuestos!$Q$22 -> 1363636.4 | AH19: =AG19*Supuestos!$D$22*Supuestos!L$7 -> 6272727.3 | AI19: =IFERROR((AH19-AG19)/AG19,"-") -> 3.6 | AJ19: =Supuestos!$C$22*Supuestos!$P$22/Supuestos!$Q$22 -> 1363636.4 | AK19: =AJ19*Supuestos!$D$22*Supuestos!M$7 -> 7090909.1 | AL19: =IFERROR((AK19-AJ19)/AJ19,"-") -> 4.2 | AM19: =C19+F19+I19+L19+O19+R19+U19+X19+AA19+AD19+AG19+AJ19 -> 15000000 | AN19: =D19+G19+J19+M19+P19+S19+V19+Y19+AB19+AE19+AH19+AK19 -> 63272727 | AO19: =IFERROR((AN19-AM19)/AM19,"-") -> 3.2181818
A20: DELIVERY Y FIDELIZACIÓN | B20: Descuento estudiantes/oficinistas (10%) | C20: =Supuestos!$C$23*Supuestos!$E$23/Supuestos!$Q$23 -> 0 | D20: =C20*Supuestos!$D$23*Supuestos!B$7 -> 0 | E20: =IFERROR((D20-C20)/C20,"-") -> - | F20: =Supuestos!$C$23*Supuestos!$F$23/Supuestos!$Q$23 -> 1250000 | G20: =F20*Supuestos!$D$23*Supuestos!C$7 -> 4312500 | H20: =IFERROR((G20-F20)/F20,"-") -> 2.45 | I20: =Supuestos!$C$23*Supuestos!$G$23/Supuestos!$Q$23 -> 1250000 | J20: =I20*Supuestos!$D$23*Supuestos!D$7 -> 3375000 | K20: =IFERROR((J20-I20)/I20,"-") -> 1.7 | L20: =Supuestos!$C$23*Supuestos!$H$23/Supuestos!$Q$23 -> 1250000 | M20: =L20*Supuestos!$D$23*Supuestos!E$7 -> 3187500 | N20: =IFERROR((M20-L20)/L20,"-") -> 1.55 | O20: =Supuestos!$C$23*Supuestos!$I$23/Supuestos!$Q$23 -> 1250000 | P20: =O20*Supuestos!$D$23*Supuestos!F$7 -> 3937500 | Q20: =IFERROR((P20-O20)/O20,"-") -> 2.15 | R20: =Supuestos!$C$23*Supuestos!$J$23/Supuestos!$Q$23 -> 0 | S20: =R20*Supuestos!$D$23*Supuestos!G$7 -> 0 | T20: =IFERROR((S20-R20)/R20,"-") -> - | U20: =Supuestos!$C$23*Supuestos!$K$23/Supuestos!$Q$23 -> 0 | V20: =U20*Supuestos!$D$23*Supuestos!H$7 -> 0 | W20: =IFERROR((V20-U20)/U20,"-") -> - | X20: =Supuestos!$C$23*Supuestos!$L$23/Supuestos!$Q$23 -> 1250000 | Y20: =X20*Supuestos!$D$23*Supuestos!I$7 -> 3937500 | Z20: =IFERROR((Y20-X20)/X20,"-") -> 2.15 | AA20: =Supuestos!$C$23*Supuestos!$M$23/Supuestos!$Q$23 -> 1250000 | AB20: =AA20*Supuestos!$D$23*Supuestos!J$7 -> 4125000 | AC20: =IFERROR((AB20-AA20)/AA20,"-") -> 2.3 | AD20: =Supuestos!$C$23*Supuestos!$N$23/Supuestos!$Q$23 -> 1250000 | AE20: =AD20*Supuestos!$D$23*Supuestos!K$7 -> 4125000 | AF20: =IFERROR((AE20-AD20)/AD20,"-") -> 2.3 | AG20: =Supuestos!$C$23*Supuestos!$O$23/Supuestos!$Q$23 -> 1250000 | AH20: =AG20*Supuestos!$D$23*Supuestos!L$7 -> 4312500 | AI20: =IFERROR((AH20-AG20)/AG20,"-") -> 2.45 | AJ20: =Supuestos!$C$23*Supuestos!$P$23/Supuestos!$Q$23 -> 0 | AK20: =AJ20*Supuestos!$D$23*Supuestos!M$7 -> 0 | AL20: =IFERROR((AK20-AJ20)/AJ20,"-") -> - | AM20: =C20+F20+I20+L20+O20+R20+U20+X20+AA20+AD20+AG20+AJ20 -> 10000000 | AN20: =D20+G20+J20+M20+P20+S20+V20+Y20+AB20+AE20+AH20+AK20 -> 31312500 | AO20: =IFERROR((AN20-AM20)/AM20,"-") -> 2.13125
A21: DELIVERY Y FIDELIZACIÓN | B21: Combo quincena (upgrade gratis 15 y 30) | C21: =Supuestos!$C$24*Supuestos!$E$24/Supuestos!$Q$24 -> 0 | D21: =C21*Supuestos!$D$24*Supuestos!B$7 -> 0 | E21: =IFERROR((D21-C21)/C21,"-") -> - | F21: =Supuestos!$C$24*Supuestos!$F$24/Supuestos!$Q$24 -> 0 | G21: =F21*Supuestos!$D$24*Supuestos!C$7 -> 0 | H21: =IFERROR((G21-F21)/F21,"-") -> - | I21: =Supuestos!$C$24*Supuestos!$G$24/Supuestos!$Q$24 -> 900000 | J21: =I21*Supuestos!$D$24*Supuestos!D$7 -> 2835000 | K21: =IFERROR((J21-I21)/I21,"-") -> 2.15 | L21: =Supuestos!$C$24*Supuestos!$H$24/Supuestos!$Q$24 -> 900000 | M21: =L21*Supuestos!$D$24*Supuestos!E$7 -> 2677500 | N21: =IFERROR((M21-L21)/L21,"-") -> 1.975 | O21: =Supuestos!$C$24*Supuestos!$I$24/Supuestos!$Q$24 -> 900000 | P21: =O21*Supuestos!$D$24*Supuestos!F$7 -> 3307500 | Q21: =IFERROR((P21-O21)/O21,"-") -> 2.675 | R21: =Supuestos!$C$24*Supuestos!$J$24/Supuestos!$Q$24 -> 900000 | S21: =R21*Supuestos!$D$24*Supuestos!G$7 -> 2992500 | T21: =IFERROR((S21-R21)/R21,"-") -> 2.325 | U21: =Supuestos!$C$24*Supuestos!$K$24/Supuestos!$Q$24 -> 900000 | V21: =U21*Supuestos!$D$24*Supuestos!H$7 -> 3150000 | W21: =IFERROR((V21-U21)/U21,"-") -> 2.5 | X21: =Supuestos!$C$24*Supuestos!$L$24/Supuestos!$Q$24 -> 900000 | Y21: =X21*Supuestos!$D$24*Supuestos!I$7 -> 3307500 | Z21: =IFERROR((Y21-X21)/X21,"-") -> 2.675 | AA21: =Supuestos!$C$24*Supuestos!$M$24/Supuestos!$Q$24 -> 900000 | AB21: =AA21*Supuestos!$D$24*Supuestos!J$7 -> 3465000 | AC21: =IFERROR((AB21-AA21)/AA21,"-") -> 2.85 | AD21: =Supuestos!$C$24*Supuestos!$N$24/Supuestos!$Q$24 -> 900000 | AE21: =AD21*Supuestos!$D$24*Supuestos!K$7 -> 3465000 | AF21: =IFERROR((AE21-AD21)/AD21,"-") -> 2.85 | AG21: =Supuestos!$C$24*Supuestos!$O$24/Supuestos!$Q$24 -> 900000 | AH21: =AG21*Supuestos!$D$24*Supuestos!L$7 -> 3622500 | AI21: =IFERROR((AH21-AG21)/AG21,"-") -> 3.025 | AJ21: =Supuestos!$C$24*Supuestos!$P$24/Supuestos!$Q$24 -> 900000 | AK21: =AJ21*Supuestos!$D$24*Supuestos!M$7 -> 4095000 | AL21: =IFERROR((AK21-AJ21)/AJ21,"-") -> 3.55 | AM21: =C21+F21+I21+L21+O21+R21+U21+X21+AA21+AD21+AG21+AJ21 -> 9000000 | AN21: =D21+G21+J21+M21+P21+S21+V21+Y21+AB21+AE21+AH21+AK21 -> 32917500 | AO21: =IFERROR((AN21-AM21)/AM21,"-") -> 2.6575
A22: DELIVERY Y FIDELIZACIÓN | B22: Almuerzos corporativos (pedidos por WhatsApp) | C22: =Supuestos!$C$25*Supuestos!$E$25/Supuestos!$Q$25 -> 0 | D22: =C22*Supuestos!$D$25*Supuestos!B$7 -> 0 | E22: =IFERROR((D22-C22)/C22,"-") -> - | F22: =Supuestos!$C$25*Supuestos!$F$25/Supuestos!$Q$25 -> 0 | G22: =F22*Supuestos!$D$25*Supuestos!C$7 -> 0 | H22: =IFERROR((G22-F22)/F22,"-") -> - | I22: =Supuestos!$C$25*Supuestos!$G$25/Supuestos!$Q$25 -> 400000 | J22: =I22*Supuestos!$D$25*Supuestos!D$7 -> 1512000 | K22: =IFERROR((J22-I22)/I22,"-") -> 2.78 | L22: =Supuestos!$C$25*Supuestos!$H$25/Supuestos!$Q$25 -> 400000 | M22: =L22*Supuestos!$D$25*Supuestos!E$7 -> 1428000 | N22: =IFERROR((M22-L22)/L22,"-") -> 2.57 | O22: =Supuestos!$C$25*Supuestos!$I$25/Supuestos!$Q$25 -> 400000 | P22: =O22*Supuestos!$D$25*Supuestos!F$7 -> 1764000 | Q22: =IFERROR((P22-O22)/O22,"-") -> 3.41 | R22: =Supuestos!$C$25*Supuestos!$J$25/Supuestos!$Q$25 -> 400000 | S22: =R22*Supuestos!$D$25*Supuestos!G$7 -> 1596000 | T22: =IFERROR((S22-R22)/R22,"-") -> 2.99 | U22: =Supuestos!$C$25*Supuestos!$K$25/Supuestos!$Q$25 -> 400000 | V22: =U22*Supuestos!$D$25*Supuestos!H$7 -> 1680000 | W22: =IFERROR((V22-U22)/U22,"-") -> 3.2 | X22: =Supuestos!$C$25*Supuestos!$L$25/Supuestos!$Q$25 -> 400000 | Y22: =X22*Supuestos!$D$25*Supuestos!I$7 -> 1764000 | Z22: =IFERROR((Y22-X22)/X22,"-") -> 3.41 | AA22: =Supuestos!$C$25*Supuestos!$M$25/Supuestos!$Q$25 -> 400000 | AB22: =AA22*Supuestos!$D$25*Supuestos!J$7 -> 1848000 | AC22: =IFERROR((AB22-AA22)/AA22,"-") -> 3.62 | AD22: =Supuestos!$C$25*Supuestos!$N$25/Supuestos!$Q$25 -> 400000 | AE22: =AD22*Supuestos!$D$25*Supuestos!K$7 -> 1848000 | AF22: =IFERROR((AE22-AD22)/AD22,"-") -> 3.62 | AG22: =Supuestos!$C$25*Supuestos!$O$25/Supuestos!$Q$25 -> 400000 | AH22: =AG22*Supuestos!$D$25*Supuestos!L$7 -> 1932000 | AI22: =IFERROR((AH22-AG22)/AG22,"-") -> 3.83 | AJ22: =Supuestos!$C$25*Supuestos!$P$25/Supuestos!$Q$25 -> 400000 | AK22: =AJ22*Supuestos!$D$25*Supuestos!M$7 -> 2184000 | AL22: =IFERROR((AK22-AJ22)/AJ22,"-") -> 4.46 | AM22: =C22+F22+I22+L22+O22+R22+U22+X22+AA22+AD22+AG22+AJ22 -> 4000000 | AN22: =D22+G22+J22+M22+P22+S22+V22+Y22+AB22+AE22+AH22+AK22 -> 17556000 | AO22: =IFERROR((AN22-AM22)/AM22,"-") -> 3.389
A23: DELIVERY Y FIDELIZACIÓN | B23: Refiere y gana (papas gratis) | C23: =Supuestos!$C$26*Supuestos!$E$26/Supuestos!$Q$26 -> 0 | D23: =C23*Supuestos!$D$26*Supuestos!B$7 -> 0 | E23: =IFERROR((D23-C23)/C23,"-") -> - | F23: =Supuestos!$C$26*Supuestos!$F$26/Supuestos!$Q$26 -> 0 | G23: =F23*Supuestos!$D$26*Supuestos!C$7 -> 0 | H23: =IFERROR((G23-F23)/F23,"-") -> - | I23: =Supuestos!$C$26*Supuestos!$G$26/Supuestos!$Q$26 -> 0 | J23: =I23*Supuestos!$D$26*Supuestos!D$7 -> 0 | K23: =IFERROR((J23-I23)/I23,"-") -> - | L23: =Supuestos!$C$26*Supuestos!$H$26/Supuestos!$Q$26 -> 500000 | M23: =L23*Supuestos!$D$26*Supuestos!E$7 -> 1912500 | N23: =IFERROR((M23-L23)/L23,"-") -> 2.825 | O23: =Supuestos!$C$26*Supuestos!$I$26/Supuestos!$Q$26 -> 500000 | P23: =O23*Supuestos!$D$26*Supuestos!F$7 -> 2362500 | Q23: =IFERROR((P23-O23)/O23,"-") -> 3.725 | R23: =Supuestos!$C$26*Supuestos!$J$26/Supuestos!$Q$26 -> 500000 | S23: =R23*Supuestos!$D$26*Supuestos!G$7 -> 2137500 | T23: =IFERROR((S23-R23)/R23,"-") -> 3.275 | U23: =Supuestos!$C$26*Supuestos!$K$26/Supuestos!$Q$26 -> 500000 | V23: =U23*Supuestos!$D$26*Supuestos!H$7 -> 2250000 | W23: =IFERROR((V23-U23)/U23,"-") -> 3.5 | X23: =Supuestos!$C$26*Supuestos!$L$26/Supuestos!$Q$26 -> 0 | Y23: =X23*Supuestos!$D$26*Supuestos!I$7 -> 0 | Z23: =IFERROR((Y23-X23)/X23,"-") -> - | AA23: =Supuestos!$C$26*Supuestos!$M$26/Supuestos!$Q$26 -> 0 | AB23: =AA23*Supuestos!$D$26*Supuestos!J$7 -> 0 | AC23: =IFERROR((AB23-AA23)/AA23,"-") -> - | AD23: =Supuestos!$C$26*Supuestos!$N$26/Supuestos!$Q$26 -> 0 | AE23: =AD23*Supuestos!$D$26*Supuestos!K$7 -> 0 | AF23: =IFERROR((AE23-AD23)/AD23,"-") -> - | AG23: =Supuestos!$C$26*Supuestos!$O$26/Supuestos!$Q$26 -> 0 | AH23: =AG23*Supuestos!$D$26*Supuestos!L$7 -> 0 | AI23: =IFERROR((AH23-AG23)/AG23,"-") -> - | AJ23: =Supuestos!$C$26*Supuestos!$P$26/Supuestos!$Q$26 -> 0 | AK23: =AJ23*Supuestos!$D$26*Supuestos!M$7 -> 0 | AL23: =IFERROR((AK23-AJ23)/AJ23,"-") -> - | AM23: =C23+F23+I23+L23+O23+R23+U23+X23+AA23+AD23+AG23+AJ23 -> 2000000 | AN23: =D23+G23+J23+M23+P23+S23+V23+Y23+AB23+AE23+AH23+AK23 -> 8662500 | AO23: =IFERROR((AN23-AM23)/AM23,"-") -> 3.33125
A24: DELIVERY Y FIDELIZACIÓN | B24: Temporada de lluvias (envío gratis) | C24: =Supuestos!$C$27*Supuestos!$E$27/Supuestos!$Q$27 -> 0 | D24: =C24*Supuestos!$D$27*Supuestos!B$7 -> 0 | E24: =IFERROR((D24-C24)/C24,"-") -> - | F24: =Supuestos!$C$27*Supuestos!$F$27/Supuestos!$Q$27 -> 0 | G24: =F24*Supuestos!$D$27*Supuestos!C$7 -> 0 | H24: =IFERROR((G24-F24)/F24,"-") -> - | I24: =Supuestos!$C$27*Supuestos!$G$27/Supuestos!$Q$27 -> 0 | J24: =I24*Supuestos!$D$27*Supuestos!D$7 -> 0 | K24: =IFERROR((J24-I24)/I24,"-") -> - | L24: =Supuestos!$C$27*Supuestos!$H$27/Supuestos!$Q$27 -> 0 | M24: =L24*Supuestos!$D$27*Supuestos!E$7 -> 0 | N24: =IFERROR((M24-L24)/L24,"-") -> - | O24: =Supuestos!$C$27*Supuestos!$I$27/Supuestos!$Q$27 -> 0 | P24: =O24*Supuestos!$D$27*Supuestos!F$7 -> 0 | Q24: =IFERROR((P24-O24)/O24,"-") -> - | R24: =Supuestos!$C$27*Supuestos!$J$27/Supuestos!$Q$27 -> 0 | S24: =R24*Supuestos!$D$27*Supuestos!G$7 -> 0 | T24: =IFERROR((S24-R24)/R24,"-") -> - | U24: =Supuestos!$C$27*Supuestos!$K$27/Supuestos!$Q$27 -> 0 | V24: =U24*Supuestos!$D$27*Supuestos!H$7 -> 0 | W24: =IFERROR((V24-U24)/U24,"-") -> - | X24: =Supuestos!$C$27*Supuestos!$L$27/Supuestos!$Q$27 -> 0 | Y24: =X24*Supuestos!$D$27*Supuestos!I$7 -> 0 | Z24: =IFERROR((Y24-X24)/X24,"-") -> - | AA24: =Supuestos!$C$27*Supuestos!$M$27/Supuestos!$Q$27 -> 0 | AB24: =AA24*Supuestos!$D$27*Supuestos!J$7 -> 0 | AC24: =IFERROR((AB24-AA24)/AA24,"-") -> - | AD24: =Supuestos!$C$27*Supuestos!$N$27/Supuestos!$Q$27 -> 900000 | AE24: =AD24*Supuestos!$D$27*Supuestos!K$7 -> 2574000 | AF24: =IFERROR((AE24-AD24)/AD24,"-") -> 1.86 | AG24: =Supuestos!$C$27*Supuestos!$O$27/Supuestos!$Q$27 -> 900000 | AH24: =AG24*Supuestos!$D$27*Supuestos!L$7 -> 2691000 | AI24: =IFERROR((AH24-AG24)/AG24,"-") -> 1.99 | AJ24: =Supuestos!$C$27*Supuestos!$P$27/Supuestos!$Q$27 -> 0 | AK24: =AJ24*Supuestos!$D$27*Supuestos!M$7 -> 0 | AL24: =IFERROR((AK24-AJ24)/AJ24,"-") -> - | AM24: =C24+F24+I24+L24+O24+R24+U24+X24+AA24+AD24+AG24+AJ24 -> 1800000 | AN24: =D24+G24+J24+M24+P24+S24+V24+Y24+AB24+AE24+AH24+AK24 -> 5265000 | AO24: =IFERROR((AN24-AM24)/AM24,"-") -> 1.925
A25: FECHAS ESPECIALES — Total | C25: =C26+C27+C28+C29+C30+C31+C32+C33+C34 -> 0 | D25: =D26+D27+D28+D29+D30+D31+D32+D33+D34 -> 0 | E25: =IFERROR((D25-C25)/C25,"-") -> - | F25: =F26+F27+F28+F29+F30+F31+F32+F33+F34 -> 2500000 | G25: =G26+G27+G28+G29+G30+G31+G32+G33+G34 -> 11500000 | H25: =IFERROR((G25-F25)/F25,"-") -> 3.6 | I25: =I26+I27+I28+I29+I30+I31+I32+I33+I34 -> 1500000 | J25: =J26+J27+J28+J29+J30+J31+J32+J33+J34 -> 4050000 | K25: =IFERROR((J25-I25)/I25,"-") -> 1.7 | L25: =L26+L27+L28+L29+L30+L31+L32+L33+L34 -> 0 | M25: =M26+M27+M28+M29+M30+M31+M32+M33+M34 -> 0 | N25: =IFERROR((M25-L25)/L25,"-") -> - | O25: =O26+O27+O28+O29+O30+O31+O32+O33+O34 -> 2500000 | P25: =P26+P27+P28+P29+P30+P31+P32+P33+P34 -> 9975000 | Q25: =IFERROR((P25-O25)/O25,"-") -> 2.99 | R25: =R26+R27+R28+R29+R30+R31+R32+R33+R34 -> 2000000 | S25: =S26+S27+S28+S29+S30+S31+S32+S33+S34 -> 6840000 | T25: =IFERROR((S25-R25)/R25,"-") -> 2.42 | U25: =U26+U27+U28+U29+U30+U31+U32+U33+U34 -> 2000000 | V25: =V26+V27+V28+V29+V30+V31+V32+V33+V34 -> 7000000 | W25: =IFERROR((V25-U25)/U25,"-") -> 2.5 | X25: =X26+X27+X28+X29+X30+X31+X32+X33+X34 -> 0 | Y25: =Y26+Y27+Y28+Y29+Y30+Y31+Y32+Y33+Y34 -> 0 | Z25: =IFERROR((Y25-X25)/X25,"-") -> - | AA25: =AA26+AA27+AA28+AA29+AA30+AA31+AA32+AA33+AA34 -> 2200000 | AB25: =AB26+AB27+AB28+AB29+AB30+AB31+AB32+AB33+AB34 -> 9680000 | AC25: =IFERROR((AB25-AA25)/AA25,"-") -> 3.4 | AD25: =AD26+AD27+AD28+AD29+AD30+AD31+AD32+AD33+AD34 -> 2500000 | AE25: =AE26+AE27+AE28+AE29+AE30+AE31+AE32+AE33+AE34 -> 8800000 | AF25: =IFERROR((AE25-AD25)/AD25,"-") -> 2.52 | AG25: =AG26+AG27+AG28+AG29+AG30+AG31+AG32+AG33+AG34 -> 2000000 | AH25: =AH26+AH27+AH28+AH29+AH30+AH31+AH32+AH33+AH34 -> 10350000 | AI25: =IFERROR((AH25-AG25)/AG25,"-") -> 4.175 | AJ25: =AJ26+AJ27+AJ28+AJ29+AJ30+AJ31+AJ32+AJ33+AJ34 -> 3500000 | AK25: =AK26+AK27+AK28+AK29+AK30+AK31+AK32+AK33+AK34 -> 22750000 | AL25: =IFERROR((AK25-AJ25)/AJ25,"-") -> 5.5 | AM25: =C25+F25+I25+L25+O25+R25+U25+X25+AA25+AD25+AG25+AJ25 -> 20700000 | AN25: =D25+G25+J25+M25+P25+S25+V25+Y25+AB25+AE25+AH25+AK25 -> 90945000 | AO25: =IFERROR((AN25-AM25)/AM25,"-") -> 3.3934783
A26: FECHAS ESPECIALES | B26: San Valentín (Comparte un Döner) | C26: =Supuestos!$C$28*Supuestos!$E$28/Supuestos!$Q$28 -> 0 | D26: =C26*Supuestos!$D$28*Supuestos!B$7 -> 0 | E26: =IFERROR((D26-C26)/C26,"-") -> - | F26: =Supuestos!$C$28*Supuestos!$F$28/Supuestos!$Q$28 -> 2500000 | G26: =F26*Supuestos!$D$28*Supuestos!C$7 -> 11500000 | H26: =IFERROR((G26-F26)/F26,"-") -> 3.6 | I26: =Supuestos!$C$28*Supuestos!$G$28/Supuestos!$Q$28 -> 0 | J26: =I26*Supuestos!$D$28*Supuestos!D$7 -> 0 | K26: =IFERROR((J26-I26)/I26,"-") -> - | L26: =Supuestos!$C$28*Supuestos!$H$28/Supuestos!$Q$28 -> 0 | M26: =L26*Supuestos!$D$28*Supuestos!E$7 -> 0 | N26: =IFERROR((M26-L26)/L26,"-") -> - | O26: =Supuestos!$C$28*Supuestos!$I$28/Supuestos!$Q$28 -> 0 | P26: =O26*Supuestos!$D$28*Supuestos!F$7 -> 0 | Q26: =IFERROR((P26-O26)/O26,"-") -> - | R26: =Supuestos!$C$28*Supuestos!$J$28/Supuestos!$Q$28 -> 0 | S26: =R26*Supuestos!$D$28*Supuestos!G$7 -> 0 | T26: =IFERROR((S26-R26)/R26,"-") -> - | U26: =Supuestos!$C$28*Supuestos!$K$28/Supuestos!$Q$28 -> 0 | V26: =U26*Supuestos!$D$28*Supuestos!H$7 -> 0 | W26: =IFERROR((V26-U26)/U26,"-") -> - | X26: =Supuestos!$C$28*Supuestos!$L$28/Supuestos!$Q$28 -> 0 | Y26: =X26*Supuestos!$D$28*Supuestos!I$7 -> 0 | Z26: =IFERROR((Y26-X26)/X26,"-") -> - | AA26: =Supuestos!$C$28*Supuestos!$M$28/Supuestos!$Q$28 -> 0 | AB26: =AA26*Supuestos!$D$28*Supuestos!J$7 -> 0 | AC26: =IFERROR((AB26-AA26)/AA26,"-") -> - | AD26: =Supuestos!$C$28*Supuestos!$N$28/Supuestos!$Q$28 -> 0 | AE26: =AD26*Supuestos!$D$28*Supuestos!K$7 -> 0 | AF26: =IFERROR((AE26-AD26)/AD26,"-") -> - | AG26: =Supuestos!$C$28*Supuestos!$O$28/Supuestos!$Q$28 -> 0 | AH26: =AG26*Supuestos!$D$28*Supuestos!L$7 -> 0 | AI26: =IFERROR((AH26-AG26)/AG26,"-") -> - | AJ26: =Supuestos!$C$28*Supuestos!$P$28/Supuestos!$Q$28 -> 0 | AK26: =AJ26*Supuestos!$D$28*Supuestos!M$7 -> 0 | AL26: =IFERROR((AK26-AJ26)/AJ26,"-") -> - | AM26: =C26+F26+I26+L26+O26+R26+U26+X26+AA26+AD26+AG26+AJ26 -> 2500000 | AN26: =D26+G26+J26+M26+P26+S26+V26+Y26+AB26+AE26+AH26+AK26 -> 11500000 | AO26: =IFERROR((AN26-AM26)/AM26,"-") -> 3.6
A27: FECHAS ESPECIALES | B27: Semana Santa (promo domicilios) | C27: =Supuestos!$C$29*Supuestos!$E$29/Supuestos!$Q$29 -> 0 | D27: =C27*Supuestos!$D$29*Supuestos!B$7 -> 0 | E27: =IFERROR((D27-C27)/C27,"-") -> - | F27: =Supuestos!$C$29*Supuestos!$F$29/Supuestos!$Q$29 -> 0 | G27: =F27*Supuestos!$D$29*Supuestos!C$7 -> 0 | H27: =IFERROR((G27-F27)/F27,"-") -> - | I27: =Supuestos!$C$29*Supuestos!$G$29/Supuestos!$Q$29 -> 1500000 | J27: =I27*Supuestos!$D$29*Supuestos!D$7 -> 4050000 | K27: =IFERROR((J27-I27)/I27,"-") -> 1.7 | L27: =Supuestos!$C$29*Supuestos!$H$29/Supuestos!$Q$29 -> 0 | M27: =L27*Supuestos!$D$29*Supuestos!E$7 -> 0 | N27: =IFERROR((M27-L27)/L27,"-") -> - | O27: =Supuestos!$C$29*Supuestos!$I$29/Supuestos!$Q$29 -> 0 | P27: =O27*Supuestos!$D$29*Supuestos!F$7 -> 0 | Q27: =IFERROR((P27-O27)/O27,"-") -> - | R27: =Supuestos!$C$29*Supuestos!$J$29/Supuestos!$Q$29 -> 0 | S27: =R27*Supuestos!$D$29*Supuestos!G$7 -> 0 | T27: =IFERROR((S27-R27)/R27,"-") -> - | U27: =Supuestos!$C$29*Supuestos!$K$29/Supuestos!$Q$29 -> 0 | V27: =U27*Supuestos!$D$29*Supuestos!H$7 -> 0 | W27: =IFERROR((V27-U27)/U27,"-") -> - | X27: =Supuestos!$C$29*Supuestos!$L$29/Supuestos!$Q$29 -> 0 | Y27: =X27*Supuestos!$D$29*Supuestos!I$7 -> 0 | Z27: =IFERROR((Y27-X27)/X27,"-") -> - | AA27: =Supuestos!$C$29*Supuestos!$M$29/Supuestos!$Q$29 -> 0 | AB27: =AA27*Supuestos!$D$29*Supuestos!J$7 -> 0 | AC27: =IFERROR((AB27-AA27)/AA27,"-") -> - | AD27: =Supuestos!$C$29*Supuestos!$N$29/Supuestos!$Q$29 -> 0 | AE27: =AD27*Supuestos!$D$29*Supuestos!K$7 -> 0 | AF27: =IFERROR((AE27-AD27)/AD27,"-") -> - | AG27: =Supuestos!$C$29*Supuestos!$O$29/Supuestos!$Q$29 -> 0 | AH27: =AG27*Supuestos!$D$29*Supuestos!L$7 -> 0 | AI27: =IFERROR((AH27-AG27)/AG27,"-") -> - | AJ27: =Supuestos!$C$29*Supuestos!$P$29/Supuestos!$Q$29 -> 0 | AK27: =AJ27*Supuestos!$D$29*Supuestos!M$7 -> 0 | AL27: =IFERROR((AK27-AJ27)/AJ27,"-") -> - | AM27: =C27+F27+I27+L27+O27+R27+U27+X27+AA27+AD27+AG27+AJ27 -> 1500000 | AN27: =D27+G27+J27+M27+P27+S27+V27+Y27+AB27+AE27+AH27+AK27 -> 4050000 | AO27: =IFERROR((AN27-AM27)/AM27,"-") -> 1.7
A28: FECHAS ESPECIALES | B28: Día de la Madre (Combo Familiar) | C28: =Supuestos!$C$30*Supuestos!$E$30/Supuestos!$Q$30 -> 0 | D28: =C28*Supuestos!$D$30*Supuestos!B$7 -> 0 | E28: =IFERROR((D28-C28)/C28,"-") -> - | F28: =Supuestos!$C$30*Supuestos!$F$30/Supuestos!$Q$30 -> 0 | G28: =F28*Supuestos!$D$30*Supuestos!C$7 -> 0 | H28: =IFERROR((G28-F28)/F28,"-") -> - | I28: =Supuestos!$C$30*Supuestos!$G$30/Supuestos!$Q$30 -> 0 | J28: =I28*Supuestos!$D$30*Supuestos!D$7 -> 0 | K28: =IFERROR((J28-I28)/I28,"-") -> - | L28: =Supuestos!$C$30*Supuestos!$H$30/Supuestos!$Q$30 -> 0 | M28: =L28*Supuestos!$D$30*Supuestos!E$7 -> 0 | N28: =IFERROR((M28-L28)/L28,"-") -> - | O28: =Supuestos!$C$30*Supuestos!$I$30/Supuestos!$Q$30 -> 2500000 | P28: =O28*Supuestos!$D$30*Supuestos!F$7 -> 9975000 | Q28: =IFERROR((P28-O28)/O28,"-") -> 2.99 | R28: =Supuestos!$C$30*Supuestos!$J$30/Supuestos!$Q$30 -> 0 | S28: =R28*Supuestos!$D$30*Supuestos!G$7 -> 0 | T28: =IFERROR((S28-R28)/R28,"-") -> - | U28: =Supuestos!$C$30*Supuestos!$K$30/Supuestos!$Q$30 -> 0 | V28: =U28*Supuestos!$D$30*Supuestos!H$7 -> 0 | W28: =IFERROR((V28-U28)/U28,"-") -> - | X28: =Supuestos!$C$30*Supuestos!$L$30/Supuestos!$Q$30 -> 0 | Y28: =X28*Supuestos!$D$30*Supuestos!I$7 -> 0 | Z28: =IFERROR((Y28-X28)/X28,"-") -> - | AA28: =Supuestos!$C$30*Supuestos!$M$30/Supuestos!$Q$30 -> 0 | AB28: =AA28*Supuestos!$D$30*Supuestos!J$7 -> 0 | AC28: =IFERROR((AB28-AA28)/AA28,"-") -> - | AD28: =Supuestos!$C$30*Supuestos!$N$30/Supuestos!$Q$30 -> 0 | AE28: =AD28*Supuestos!$D$30*Supuestos!K$7 -> 0 | AF28: =IFERROR((AE28-AD28)/AD28,"-") -> - | AG28: =Supuestos!$C$30*Supuestos!$O$30/Supuestos!$Q$30 -> 0 | AH28: =AG28*Supuestos!$D$30*Supuestos!L$7 -> 0 | AI28: =IFERROR((AH28-AG28)/AG28,"-") -> - | AJ28: =Supuestos!$C$30*Supuestos!$P$30/Supuestos!$Q$30 -> 0 | AK28: =AJ28*Supuestos!$D$30*Supuestos!M$7 -> 0 | AL28: =IFERROR((AK28-AJ28)/AJ28,"-") -> - | AM28: =C28+F28+I28+L28+O28+R28+U28+X28+AA28+AD28+AG28+AJ28 -> 2500000 | AN28: =D28+G28+J28+M28+P28+S28+V28+Y28+AB28+AE28+AH28+AK28 -> 9975000 | AO28: =IFERROR((AN28-AM28)/AM28,"-") -> 2.99
A29: FECHAS ESPECIALES | B29: Día del Padre (Combo Grande especial) | C29: =Supuestos!$C$31*Supuestos!$E$31/Supuestos!$Q$31 -> 0 | D29: =C29*Supuestos!$D$31*Supuestos!B$7 -> 0 | E29: =IFERROR((D29-C29)/C29,"-") -> - | F29: =Supuestos!$C$31*Supuestos!$F$31/Supuestos!$Q$31 -> 0 | G29: =F29*Supuestos!$D$31*Supuestos!C$7 -> 0 | H29: =IFERROR((G29-F29)/F29,"-") -> - | I29: =Supuestos!$C$31*Supuestos!$G$31/Supuestos!$Q$31 -> 0 | J29: =I29*Supuestos!$D$31*Supuestos!D$7 -> 0 | K29: =IFERROR((J29-I29)/I29,"-") -> - | L29: =Supuestos!$C$31*Supuestos!$H$31/Supuestos!$Q$31 -> 0 | M29: =L29*Supuestos!$D$31*Supuestos!E$7 -> 0 | N29: =IFERROR((M29-L29)/L29,"-") -> - | O29: =Supuestos!$C$31*Supuestos!$I$31/Supuestos!$Q$31 -> 0 | P29: =O29*Supuestos!$D$31*Supuestos!F$7 -> 0 | Q29: =IFERROR((P29-O29)/O29,"-") -> - | R29: =Supuestos!$C$31*Supuestos!$J$31/Supuestos!$Q$31 -> 2000000 | S29: =R29*Supuestos!$D$31*Supuestos!G$7 -> 6840000 | T29: =IFERROR((S29-R29)/R29,"-") -> 2.42 | U29: =Supuestos!$C$31*Supuestos!$K$31/Supuestos!$Q$31 -> 0 | V29: =U29*Supuestos!$D$31*Supuestos!H$7 -> 0 | W29: =IFERROR((V29-U29)/U29,"-") -> - | X29: =Supuestos!$C$31*Supuestos!$L$31/Supuestos!$Q$31 -> 0 | Y29: =X29*Supuestos!$D$31*Supuestos!I$7 -> 0 | Z29: =IFERROR((Y29-X29)/X29,"-") -> - | AA29: =Supuestos!$C$31*Supuestos!$M$31/Supuestos!$Q$31 -> 0 | AB29: =AA29*Supuestos!$D$31*Supuestos!J$7 -> 0 | AC29: =IFERROR((AB29-AA29)/AA29,"-") -> - | AD29: =Supuestos!$C$31*Supuestos!$N$31/Supuestos!$Q$31 -> 0 | AE29: =AD29*Supuestos!$D$31*Supuestos!K$7 -> 0 | AF29: =IFERROR((AE29-AD29)/AD29,"-") -> - | AG29: =Supuestos!$C$31*Supuestos!$O$31/Supuestos!$Q$31 -> 0 | AH29: =AG29*Supuestos!$D$31*Supuestos!L$7 -> 0 | AI29: =IFERROR((AH29-AG29)/AG29,"-") -> - | AJ29: =Supuestos!$C$31*Supuestos!$P$31/Supuestos!$Q$31 -> 0 | AK29: =AJ29*Supuestos!$D$31*Supuestos!M$7 -> 0 | AL29: =IFERROR((AK29-AJ29)/AJ29,"-") -> - | AM29: =C29+F29+I29+L29+O29+R29+U29+X29+AA29+AD29+AG29+AJ29 -> 2000000 | AN29: =D29+G29+J29+M29+P29+S29+V29+Y29+AB29+AE29+AH29+AK29 -> 6840000 | AO29: =IFERROR((AN29-AM29)/AM29,"-") -> 2.42
A30: FECHAS ESPECIALES | B30: Aniversario 6 meses (upgrade gratis) | C30: =Supuestos!$C$32*Supuestos!$E$32/Supuestos!$Q$32 -> 0 | D30: =C30*Supuestos!$D$32*Supuestos!B$7 -> 0 | E30: =IFERROR((D30-C30)/C30,"-") -> - | F30: =Supuestos!$C$32*Supuestos!$F$32/Supuestos!$Q$32 -> 0 | G30: =F30*Supuestos!$D$32*Supuestos!C$7 -> 0 | H30: =IFERROR((G30-F30)/F30,"-") -> - | I30: =Supuestos!$C$32*Supuestos!$G$32/Supuestos!$Q$32 -> 0 | J30: =I30*Supuestos!$D$32*Supuestos!D$7 -> 0 | K30: =IFERROR((J30-I30)/I30,"-") -> - | L30: =Supuestos!$C$32*Supuestos!$H$32/Supuestos!$Q$32 -> 0 | M30: =L30*Supuestos!$D$32*Supuestos!E$7 -> 0 | N30: =IFERROR((M30-L30)/L30,"-") -> - | O30: =Supuestos!$C$32*Supuestos!$I$32/Supuestos!$Q$32 -> 0 | P30: =O30*Supuestos!$D$32*Supuestos!F$7 -> 0 | Q30: =IFERROR((P30-O30)/O30,"-") -> - | R30: =Supuestos!$C$32*Supuestos!$J$32/Supuestos!$Q$32 -> 0 | S30: =R30*Supuestos!$D$32*Supuestos!G$7 -> 0 | T30: =IFERROR((S30-R30)/R30,"-") -> - | U30: =Supuestos!$C$32*Supuestos!$K$32/Supuestos!$Q$32 -> 2000000 | V30: =U30*Supuestos!$D$32*Supuestos!H$7 -> 7000000 | W30: =IFERROR((V30-U30)/U30,"-") -> 2.5 | X30: =Supuestos!$C$32*Supuestos!$L$32/Supuestos!$Q$32 -> 0 | Y30: =X30*Supuestos!$D$32*Supuestos!I$7 -> 0 | Z30: =IFERROR((Y30-X30)/X30,"-") -> - | AA30: =Supuestos!$C$32*Supuestos!$M$32/Supuestos!$Q$32 -> 0 | AB30: =AA30*Supuestos!$D$32*Supuestos!J$7 -> 0 | AC30: =IFERROR((AB30-AA30)/AA30,"-") -> - | AD30: =Supuestos!$C$32*Supuestos!$N$32/Supuestos!$Q$32 -> 0 | AE30: =AD30*Supuestos!$D$32*Supuestos!K$7 -> 0 | AF30: =IFERROR((AE30-AD30)/AD30,"-") -> - | AG30: =Supuestos!$C$32*Supuestos!$O$32/Supuestos!$Q$32 -> 0 | AH30: =AG30*Supuestos!$D$32*Supuestos!L$7 -> 0 | AI30: =IFERROR((AH30-AG30)/AG30,"-") -> - | AJ30: =Supuestos!$C$32*Supuestos!$P$32/Supuestos!$Q$32 -> 0 | AK30: =AJ30*Supuestos!$D$32*Supuestos!M$7 -> 0 | AL30: =IFERROR((AK30-AJ30)/AJ30,"-") -> - | AM30: =C30+F30+I30+L30+O30+R30+U30+X30+AA30+AD30+AG30+AJ30 -> 2000000 | AN30: =D30+G30+J30+M30+P30+S30+V30+Y30+AB30+AE30+AH30+AK30 -> 7000000 | AO30: =IFERROR((AN30-AM30)/AM30,"-") -> 2.5
A31: FECHAS ESPECIALES | B31: Amor y Amistad (Combo Amigos) | C31: =Supuestos!$C$33*Supuestos!$E$33/Supuestos!$Q$33 -> 0 | D31: =C31*Supuestos!$D$33*Supuestos!B$7 -> 0 | E31: =IFERROR((D31-C31)/C31,"-") -> - | F31: =Supuestos!$C$33*Supuestos!$F$33/Supuestos!$Q$33 -> 0 | G31: =F31*Supuestos!$D$33*Supuestos!C$7 -> 0 | H31: =IFERROR((G31-F31)/F31,"-") -> - | I31: =Supuestos!$C$33*Supuestos!$G$33/Supuestos!$Q$33 -> 0 | J31: =I31*Supuestos!$D$33*Supuestos!D$7 -> 0 | K31: =IFERROR((J31-I31)/I31,"-") -> - | L31: =Supuestos!$C$33*Supuestos!$H$33/Supuestos!$Q$33 -> 0 | M31: =L31*Supuestos!$D$33*Supuestos!E$7 -> 0 | N31: =IFERROR((M31-L31)/L31,"-") -> - | O31: =Supuestos!$C$33*Supuestos!$I$33/Supuestos!$Q$33 -> 0 | P31: =O31*Supuestos!$D$33*Supuestos!F$7 -> 0 | Q31: =IFERROR((P31-O31)/O31,"-") -> - | R31: =Supuestos!$C$33*Supuestos!$J$33/Supuestos!$Q$33 -> 0 | S31: =R31*Supuestos!$D$33*Supuestos!G$7 -> 0 | T31: =IFERROR((S31-R31)/R31,"-") -> - | U31: =Supuestos!$C$33*Supuestos!$K$33/Supuestos!$Q$33 -> 0 | V31: =U31*Supuestos!$D$33*Supuestos!H$7 -> 0 | W31: =IFERROR((V31-U31)/U31,"-") -> - | X31: =Supuestos!$C$33*Supuestos!$L$33/Supuestos!$Q$33 -> 0 | Y31: =X31*Supuestos!$D$33*Supuestos!I$7 -> 0 | Z31: =IFERROR((Y31-X31)/X31,"-") -> - | AA31: =Supuestos!$C$33*Supuestos!$M$33/Supuestos!$Q$33 -> 2200000 | AB31: =AA31*Supuestos!$D$33*Supuestos!J$7 -> 9680000 | AC31: =IFERROR((AB31-AA31)/AA31,"-") -> 3.4 | AD31: =Supuestos!$C$33*Supuestos!$N$33/Supuestos!$Q$33 -> 0 | AE31: =AD31*Supuestos!$D$33*Supuestos!K$7 -> 0 | AF31: =IFERROR((AE31-AD31)/AD31,"-") -> - | AG31: =Supuestos!$C$33*Supuestos!$O$33/Supuestos!$Q$33 -> 0 | AH31: =AG31*Supuestos!$D$33*Supuestos!L$7 -> 0 | AI31: =IFERROR((AH31-AG31)/AG31,"-") -> - | AJ31: =Supuestos!$C$33*Supuestos!$P$33/Supuestos!$Q$33 -> 0 | AK31: =AJ31*Supuestos!$D$33*Supuestos!M$7 -> 0 | AL31: =IFERROR((AK31-AJ31)/AJ31,"-") -> - | AM31: =C31+F31+I31+L31+O31+R31+U31+X31+AA31+AD31+AG31+AJ31 -> 2200000 | AN31: =D31+G31+J31+M31+P31+S31+V31+Y31+AB31+AE31+AH31+AK31 -> 9680000 | AO31: =IFERROR((AN31-AM31)/AM31,"-") -> 3.4
A32: FECHAS ESPECIALES | B32: Puente + Halloween (promo apps) | C32: =Supuestos!$C$34*Supuestos!$E$34/Supuestos!$Q$34 -> 0 | D32: =C32*Supuestos!$D$34*Supuestos!B$7 -> 0 | E32: =IFERROR((D32-C32)/C32,"-") -> - | F32: =Supuestos!$C$34*Supuestos!$F$34/Supuestos!$Q$34 -> 0 | G32: =F32*Supuestos!$D$34*Supuestos!C$7 -> 0 | H32: =IFERROR((G32-F32)/F32,"-") -> - | I32: =Supuestos!$C$34*Supuestos!$G$34/Supuestos!$Q$34 -> 0 | J32: =I32*Supuestos!$D$34*Supuestos!D$7 -> 0 | K32: =IFERROR((J32-I32)/I32,"-") -> - | L32: =Supuestos!$C$34*Supuestos!$H$34/Supuestos!$Q$34 -> 0 | M32: =L32*Supuestos!$D$34*Supuestos!E$7 -> 0 | N32: =IFERROR((M32-L32)/L32,"-") -> - | O32: =Supuestos!$C$34*Supuestos!$I$34/Supuestos!$Q$34 -> 0 | P32: =O32*Supuestos!$D$34*Supuestos!F$7 -> 0 | Q32: =IFERROR((P32-O32)/O32,"-") -> - | R32: =Supuestos!$C$34*Supuestos!$J$34/Supuestos!$Q$34 -> 0 | S32: =R32*Supuestos!$D$34*Supuestos!G$7 -> 0 | T32: =IFERROR((S32-R32)/R32,"-") -> - | U32: =Supuestos!$C$34*Supuestos!$K$34/Supuestos!$Q$34 -> 0 | V32: =U32*Supuestos!$D$34*Supuestos!H$7 -> 0 | W32: =IFERROR((V32-U32)/U32,"-") -> - | X32: =Supuestos!$C$34*Supuestos!$L$34/Supuestos!$Q$34 -> 0 | Y32: =X32*Supuestos!$D$34*Supuestos!I$7 -> 0 | Z32: =IFERROR((Y32-X32)/X32,"-") -> - | AA32: =Supuestos!$C$34*Supuestos!$M$34/Supuestos!$Q$34 -> 0 | AB32: =AA32*Supuestos!$D$34*Supuestos!J$7 -> 0 | AC32: =IFERROR((AB32-AA32)/AA32,"-") -> - | AD32: =Supuestos!$C$34*Supuestos!$N$34/Supuestos!$Q$34 -> 2500000 | AE32: =AD32*Supuestos!$D$34*Supuestos!K$7 -> 8800000 | AF32: =IFERROR((AE32-AD32)/AD32,"-") -> 2.52 | AG32: =Supuestos!$C$34*Supuestos!$O$34/Supuestos!$Q$34 -> 0 | AH32: =AG32*Supuestos!$D$34*Supuestos!L$7 -> 0 | AI32: =IFERROR((AH32-AG32)/AG32,"-") -> - | AJ32: =Supuestos!$C$34*Supuestos!$P$34/Supuestos!$Q$34 -> 0 | AK32: =AJ32*Supuestos!$D$34*Supuestos!M$7 -> 0 | AL32: =IFERROR((AK32-AJ32)/AJ32,"-") -> - | AM32: =C32+F32+I32+L32+O32+R32+U32+X32+AA32+AD32+AG32+AJ32 -> 2500000 | AN32: =D32+G32+J32+M32+P32+S32+V32+Y32+AB32+AE32+AH32+AK32 -> 8800000 | AO32: =IFERROR((AN32-AM32)/AM32,"-") -> 2.52
A33: FECHAS ESPECIALES | B33: Puente noviembre + Black Friday | C33: =Supuestos!$C$35*Supuestos!$E$35/Supuestos!$Q$35 -> 0 | D33: =C33*Supuestos!$D$35*Supuestos!B$7 -> 0 | E33: =IFERROR((D33-C33)/C33,"-") -> - | F33: =Supuestos!$C$35*Supuestos!$F$35/Supuestos!$Q$35 -> 0 | G33: =F33*Supuestos!$D$35*Supuestos!C$7 -> 0 | H33: =IFERROR((G33-F33)/F33,"-") -> - | I33: =Supuestos!$C$35*Supuestos!$G$35/Supuestos!$Q$35 -> 0 | J33: =I33*Supuestos!$D$35*Supuestos!D$7 -> 0 | K33: =IFERROR((J33-I33)/I33,"-") -> - | L33: =Supuestos!$C$35*Supuestos!$H$35/Supuestos!$Q$35 -> 0 | M33: =L33*Supuestos!$D$35*Supuestos!E$7 -> 0 | N33: =IFERROR((M33-L33)/L33,"-") -> - | O33: =Supuestos!$C$35*Supuestos!$I$35/Supuestos!$Q$35 -> 0 | P33: =O33*Supuestos!$D$35*Supuestos!F$7 -> 0 | Q33: =IFERROR((P33-O33)/O33,"-") -> - | R33: =Supuestos!$C$35*Supuestos!$J$35/Supuestos!$Q$35 -> 0 | S33: =R33*Supuestos!$D$35*Supuestos!G$7 -> 0 | T33: =IFERROR((S33-R33)/R33,"-") -> - | U33: =Supuestos!$C$35*Supuestos!$K$35/Supuestos!$Q$35 -> 0 | V33: =U33*Supuestos!$D$35*Supuestos!H$7 -> 0 | W33: =IFERROR((V33-U33)/U33,"-") -> - | X33: =Supuestos!$C$35*Supuestos!$L$35/Supuestos!$Q$35 -> 0 | Y33: =X33*Supuestos!$D$35*Supuestos!I$7 -> 0 | Z33: =IFERROR((Y33-X33)/X33,"-") -> - | AA33: =Supuestos!$C$35*Supuestos!$M$35/Supuestos!$Q$35 -> 0 | AB33: =AA33*Supuestos!$D$35*Supuestos!J$7 -> 0 | AC33: =IFERROR((AB33-AA33)/AA33,"-") -> - | AD33: =Supuestos!$C$35*Supuestos!$N$35/Supuestos!$Q$35 -> 0 | AE33: =AD33*Supuestos!$D$35*Supuestos!K$7 -> 0 | AF33: =IFERROR((AE33-AD33)/AD33,"-") -> - | AG33: =Supuestos!$C$35*Supuestos!$O$35/Supuestos!$Q$35 -> 2000000 | AH33: =AG33*Supuestos!$D$35*Supuestos!L$7 -> 10350000 | AI33: =IFERROR((AH33-AG33)/AG33,"-") -> 4.175 | AJ33: =Supuestos!$C$35*Supuestos!$P$35/Supuestos!$Q$35 -> 0 | AK33: =AJ33*Supuestos!$D$35*Supuestos!M$7 -> 0 | AL33: =IFERROR((AK33-AJ33)/AJ33,"-") -> - | AM33: =C33+F33+I33+L33+O33+R33+U33+X33+AA33+AD33+AG33+AJ33 -> 2000000 | AN33: =D33+G33+J33+M33+P33+S33+V33+Y33+AB33+AE33+AH33+AK33 -> 10350000 | AO33: =IFERROR((AN33-AM33)/AM33,"-") -> 4.175
A34: FECHAS ESPECIALES | B34: Navidad y fin de año (Party Pack) | C34: =Supuestos!$C$36*Supuestos!$E$36/Supuestos!$Q$36 -> 0 | D34: =C34*Supuestos!$D$36*Supuestos!B$7 -> 0 | E34: =IFERROR((D34-C34)/C34,"-") -> - | F34: =Supuestos!$C$36*Supuestos!$F$36/Supuestos!$Q$36 -> 0 | G34: =F34*Supuestos!$D$36*Supuestos!C$7 -> 0 | H34: =IFERROR((G34-F34)/F34,"-") -> - | I34: =Supuestos!$C$36*Supuestos!$G$36/Supuestos!$Q$36 -> 0 | J34: =I34*Supuestos!$D$36*Supuestos!D$7 -> 0 | K34: =IFERROR((J34-I34)/I34,"-") -> - | L34: =Supuestos!$C$36*Supuestos!$H$36/Supuestos!$Q$36 -> 0 | M34: =L34*Supuestos!$D$36*Supuestos!E$7 -> 0 | N34: =IFERROR((M34-L34)/L34,"-") -> - | O34: =Supuestos!$C$36*Supuestos!$I$36/Supuestos!$Q$36 -> 0 | P34: =O34*Supuestos!$D$36*Supuestos!F$7 -> 0 | Q34: =IFERROR((P34-O34)/O34,"-") -> - | R34: =Supuestos!$C$36*Supuestos!$J$36/Supuestos!$Q$36 -> 0 | S34: =R34*Supuestos!$D$36*Supuestos!G$7 -> 0 | T34: =IFERROR((S34-R34)/R34,"-") -> - | U34: =Supuestos!$C$36*Supuestos!$K$36/Supuestos!$Q$36 -> 0 | V34: =U34*Supuestos!$D$36*Supuestos!H$7 -> 0 | W34: =IFERROR((V34-U34)/U34,"-") -> - | X34: =Supuestos!$C$36*Supuestos!$L$36/Supuestos!$Q$36 -> 0 | Y34: =X34*Supuestos!$D$36*Supuestos!I$7 -> 0 | Z34: =IFERROR((Y34-X34)/X34,"-") -> - | AA34: =Supuestos!$C$36*Supuestos!$M$36/Supuestos!$Q$36 -> 0 | AB34: =AA34*Supuestos!$D$36*Supuestos!J$7 -> 0 | AC34: =IFERROR((AB34-AA34)/AA34,"-") -> - | AD34: =Supuestos!$C$36*Supuestos!$N$36/Supuestos!$Q$36 -> 0 | AE34: =AD34*Supuestos!$D$36*Supuestos!K$7 -> 0 | AF34: =IFERROR((AE34-AD34)/AD34,"-") -> - | AG34: =Supuestos!$C$36*Supuestos!$O$36/Supuestos!$Q$36 -> 0 | AH34: =AG34*Supuestos!$D$36*Supuestos!L$7 -> 0 | AI34: =IFERROR((AH34-AG34)/AG34,"-") -> - | AJ34: =Supuestos!$C$36*Supuestos!$P$36/Supuestos!$Q$36 -> 3500000 | AK34: =AJ34*Supuestos!$D$36*Supuestos!M$7 -> 22750000 | AL34: =IFERROR((AK34-AJ34)/AJ34,"-") -> 5.5 | AM34: =C34+F34+I34+L34+O34+R34+U34+X34+AA34+AD34+AG34+AJ34 -> 3500000 | AN34: =D34+G34+J34+M34+P34+S34+V34+Y34+AB34+AE34+AH34+AK34 -> 22750000 | AO34: =IFERROR((AN34-AM34)/AM34,"-") -> 5.5
A35: COMUNIDAD Y ALIANZAS — Total | C35: =C36+C37+C38+C39+C40 -> 0 | D35: =D36+D37+D38+D39+D40 -> 0 | E35: =IFERROR((D35-C35)/C35,"-") -> - | F35: =F36+F37+F38+F39+F40 -> 1000000 | G35: =G36+G37+G38+G39+G40 -> 3450000 | H35: =IFERROR((G35-F35)/F35,"-") -> 2.45 | I35: =I36+I37+I38+I39+I40 -> 1000000 | J35: =J36+J37+J38+J39+J40 -> 2520000 | K35: =IFERROR((J35-I35)/I35,"-") -> 1.52 | L35: =L36+L37+L38+L39+L40 -> 1000000 | M35: =M36+M37+M38+M39+M40 -> 2380000 | N35: =IFERROR((M35-L35)/L35,"-") -> 1.38 | O35: =O36+O37+O38+O39+O40 -> 2500000 | P35: =P36+P37+P38+P39+P40 -> 7665000 | Q35: =IFERROR((P35-O35)/O35,"-") -> 2.066 | R35: =R36+R37+R38+R39+R40 -> 0 | S35: =S36+S37+S38+S39+S40 -> 0 | T35: =IFERROR((S35-R35)/R35,"-") -> - | U35: =U36+U37+U38+U39+U40 -> 0 | V35: =V36+V37+V38+V39+V40 -> 0 | W35: =IFERROR((V35-U35)/U35,"-") -> - | X35: =X36+X37+X38+X39+X40 -> 2250000 | Y35: =Y36+Y37+Y38+Y39+Y40 -> 6431250 | Z35: =IFERROR((Y35-X35)/X35,"-") -> 1.8583333 | AA35: =AA36+AA37+AA38+AA39+AA40 -> 1250000 | AB35: =AB36+AB37+AB38+AB39+AB40 -> 3437500 | AC35: =IFERROR((AB35-AA35)/AA35,"-") -> 1.75 | AD35: =AD36+AD37+AD38+AD39+AD40 -> 900000 | AE35: =AE36+AE37+AE38+AE39+AE40 -> 1782000 | AF35: =IFERROR((AE35-AD35)/AD35,"-") -> 0.98 | AG35: =AG36+AG37+AG38+AG39+AG40 -> 900000 | AH35: =AH36+AH37+AH38+AH39+AH40 -> 1863000 | AI35: =IFERROR((AH35-AG35)/AG35,"-") -> 1.07 | AJ35: =AJ36+AJ37+AJ38+AJ39+AJ40 -> 0 | AK35: =AK36+AK37+AK38+AK39+AK40 -> 0 | AL35: =IFERROR((AK35-AJ35)/AJ35,"-") -> - | AM35: =C35+F35+I35+L35+O35+R35+U35+X35+AA35+AD35+AG35+AJ35 -> 10800000 | AN35: =D35+G35+J35+M35+P35+S35+V35+Y35+AB35+AE35+AH35+AK35 -> 29528750 | AO35: =IFERROR((AN35-AM35)/AM35,"-") -> 1.7341435
A36: COMUNIDAD Y ALIANZAS | B36: Semana de bienvenida universitaria | C36: =Supuestos!$C$37*Supuestos!$E$37/Supuestos!$Q$37 -> 0 | D36: =C36*Supuestos!$D$37*Supuestos!B$7 -> 0 | E36: =IFERROR((D36-C36)/C36,"-") -> - | F36: =Supuestos!$C$37*Supuestos!$F$37/Supuestos!$Q$37 -> 1000000 | G36: =F36*Supuestos!$D$37*Supuestos!C$7 -> 3450000 | H36: =IFERROR((G36-F36)/F36,"-") -> 2.45 | I36: =Supuestos!$C$37*Supuestos!$G$37/Supuestos!$Q$37 -> 0 | J36: =I36*Supuestos!$D$37*Supuestos!D$7 -> 0 | K36: =IFERROR((J36-I36)/I36,"-") -> - | L36: =Supuestos!$C$37*Supuestos!$H$37/Supuestos!$Q$37 -> 0 | M36: =L36*Supuestos!$D$37*Supuestos!E$7 -> 0 | N36: =IFERROR((M36-L36)/L36,"-") -> - | O36: =Supuestos!$C$37*Supuestos!$I$37/Supuestos!$Q$37 -> 0 | P36: =O36*Supuestos!$D$37*Supuestos!F$7 -> 0 | Q36: =IFERROR((P36-O36)/O36,"-") -> - | R36: =Supuestos!$C$37*Supuestos!$J$37/Supuestos!$Q$37 -> 0 | S36: =R36*Supuestos!$D$37*Supuestos!G$7 -> 0 | T36: =IFERROR((S36-R36)/R36,"-") -> - | U36: =Supuestos!$C$37*Supuestos!$K$37/Supuestos!$Q$37 -> 0 | V36: =U36*Supuestos!$D$37*Supuestos!H$7 -> 0 | W36: =IFERROR((V36-U36)/U36,"-") -> - | X36: =Supuestos!$C$37*Supuestos!$L$37/Supuestos!$Q$37 -> 1000000 | Y36: =X36*Supuestos!$D$37*Supuestos!I$7 -> 3150000 | Z36: =IFERROR((Y36-X36)/X36,"-") -> 2.15 | AA36: =Supuestos!$C$37*Supuestos!$M$37/Supuestos!$Q$37 -> 0 | AB36: =AA36*Supuestos!$D$37*Supuestos!J$7 -> 0 | AC36: =IFERROR((AB36-AA36)/AA36,"-") -> - | AD36: =Supuestos!$C$37*Supuestos!$N$37/Supuestos!$Q$37 -> 0 | AE36: =AD36*Supuestos!$D$37*Supuestos!K$7 -> 0 | AF36: =IFERROR((AE36-AD36)/AD36,"-") -> - | AG36: =Supuestos!$C$37*Supuestos!$O$37/Supuestos!$Q$37 -> 0 | AH36: =AG36*Supuestos!$D$37*Supuestos!L$7 -> 0 | AI36: =IFERROR((AH36-AG36)/AG36,"-") -> - | AJ36: =Supuestos!$C$37*Supuestos!$P$37/Supuestos!$Q$37 -> 0 | AK36: =AJ36*Supuestos!$D$37*Supuestos!M$7 -> 0 | AL36: =IFERROR((AK36-AJ36)/AJ36,"-") -> - | AM36: =C36+F36+I36+L36+O36+R36+U36+X36+AA36+AD36+AG36+AJ36 -> 2000000 | AN36: =D36+G36+J36+M36+P36+S36+V36+Y36+AB36+AE36+AH36+AK36 -> 6600000 | AO36: =IFERROR((AN36-AM36)/AM36,"-") -> 2.3
A37: COMUNIDAD Y ALIANZAS | B37: Alianzas gimnasios y coworking | C37: =Supuestos!$C$38*Supuestos!$E$38/Supuestos!$Q$38 -> 0 | D37: =C37*Supuestos!$D$38*Supuestos!B$7 -> 0 | E37: =IFERROR((D37-C37)/C37,"-") -> - | F37: =Supuestos!$C$38*Supuestos!$F$38/Supuestos!$Q$38 -> 0 | G37: =F37*Supuestos!$D$38*Supuestos!C$7 -> 0 | H37: =IFERROR((G37-F37)/F37,"-") -> - | I37: =Supuestos!$C$38*Supuestos!$G$38/Supuestos!$Q$38 -> 1000000 | J37: =I37*Supuestos!$D$38*Supuestos!D$7 -> 2520000 | K37: =IFERROR((J37-I37)/I37,"-") -> 1.52 | L37: =Supuestos!$C$38*Supuestos!$H$38/Supuestos!$Q$38 -> 1000000 | M37: =L37*Supuestos!$D$38*Supuestos!E$7 -> 2380000 | N37: =IFERROR((M37-L37)/L37,"-") -> 1.38 | O37: =Supuestos!$C$38*Supuestos!$I$38/Supuestos!$Q$38 -> 1000000 | P37: =O37*Supuestos!$D$38*Supuestos!F$7 -> 2940000 | Q37: =IFERROR((P37-O37)/O37,"-") -> 1.94 | R37: =Supuestos!$C$38*Supuestos!$J$38/Supuestos!$Q$38 -> 0 | S37: =R37*Supuestos!$D$38*Supuestos!G$7 -> 0 | T37: =IFERROR((S37-R37)/R37,"-") -> - | U37: =Supuestos!$C$38*Supuestos!$K$38/Supuestos!$Q$38 -> 0 | V37: =U37*Supuestos!$D$38*Supuestos!H$7 -> 0 | W37: =IFERROR((V37-U37)/U37,"-") -> - | X37: =Supuestos!$C$38*Supuestos!$L$38/Supuestos!$Q$38 -> 0 | Y37: =X37*Supuestos!$D$38*Supuestos!I$7 -> 0 | Z37: =IFERROR((Y37-X37)/X37,"-") -> - | AA37: =Supuestos!$C$38*Supuestos!$M$38/Supuestos!$Q$38 -> 0 | AB37: =AA37*Supuestos!$D$38*Supuestos!J$7 -> 0 | AC37: =IFERROR((AB37-AA37)/AA37,"-") -> - | AD37: =Supuestos!$C$38*Supuestos!$N$38/Supuestos!$Q$38 -> 0 | AE37: =AD37*Supuestos!$D$38*Supuestos!K$7 -> 0 | AF37: =IFERROR((AE37-AD37)/AD37,"-") -> - | AG37: =Supuestos!$C$38*Supuestos!$O$38/Supuestos!$Q$38 -> 0 | AH37: =AG37*Supuestos!$D$38*Supuestos!L$7 -> 0 | AI37: =IFERROR((AH37-AG37)/AG37,"-") -> - | AJ37: =Supuestos!$C$38*Supuestos!$P$38/Supuestos!$Q$38 -> 0 | AK37: =AJ37*Supuestos!$D$38*Supuestos!M$7 -> 0 | AL37: =IFERROR((AK37-AJ37)/AJ37,"-") -> - | AM37: =C37+F37+I37+L37+O37+R37+U37+X37+AA37+AD37+AG37+AJ37 -> 3000000 | AN37: =D37+G37+J37+M37+P37+S37+V37+Y37+AB37+AE37+AH37+AK37 -> 7840000 | AO37: =IFERROR((AN37-AM37)/AM37,"-") -> 1.6133333
A38: COMUNIDAD Y ALIANZAS | B38: Degustación de barrio (Calle 72) | C38: =Supuestos!$C$39*Supuestos!$E$39/Supuestos!$Q$39 -> 0 | D38: =C38*Supuestos!$D$39*Supuestos!B$7 -> 0 | E38: =IFERROR((D38-C38)/C38,"-") -> - | F38: =Supuestos!$C$39*Supuestos!$F$39/Supuestos!$Q$39 -> 0 | G38: =F38*Supuestos!$D$39*Supuestos!C$7 -> 0 | H38: =IFERROR((G38-F38)/F38,"-") -> - | I38: =Supuestos!$C$39*Supuestos!$G$39/Supuestos!$Q$39 -> 0 | J38: =I38*Supuestos!$D$39*Supuestos!D$7 -> 0 | K38: =IFERROR((J38-I38)/I38,"-") -> - | L38: =Supuestos!$C$39*Supuestos!$H$39/Supuestos!$Q$39 -> 0 | M38: =L38*Supuestos!$D$39*Supuestos!E$7 -> 0 | N38: =IFERROR((M38-L38)/L38,"-") -> - | O38: =Supuestos!$C$39*Supuestos!$I$39/Supuestos!$Q$39 -> 1500000 | P38: =O38*Supuestos!$D$39*Supuestos!F$7 -> 4725000 | Q38: =IFERROR((P38-O38)/O38,"-") -> 2.15 | R38: =Supuestos!$C$39*Supuestos!$J$39/Supuestos!$Q$39 -> 0 | S38: =R38*Supuestos!$D$39*Supuestos!G$7 -> 0 | T38: =IFERROR((S38-R38)/R38,"-") -> - | U38: =Supuestos!$C$39*Supuestos!$K$39/Supuestos!$Q$39 -> 0 | V38: =U38*Supuestos!$D$39*Supuestos!H$7 -> 0 | W38: =IFERROR((V38-U38)/U38,"-") -> - | X38: =Supuestos!$C$39*Supuestos!$L$39/Supuestos!$Q$39 -> 0 | Y38: =X38*Supuestos!$D$39*Supuestos!I$7 -> 0 | Z38: =IFERROR((Y38-X38)/X38,"-") -> - | AA38: =Supuestos!$C$39*Supuestos!$M$39/Supuestos!$Q$39 -> 0 | AB38: =AA38*Supuestos!$D$39*Supuestos!J$7 -> 0 | AC38: =IFERROR((AB38-AA38)/AA38,"-") -> - | AD38: =Supuestos!$C$39*Supuestos!$N$39/Supuestos!$Q$39 -> 0 | AE38: =AD38*Supuestos!$D$39*Supuestos!K$7 -> 0 | AF38: =IFERROR((AE38-AD38)/AD38,"-") -> - | AG38: =Supuestos!$C$39*Supuestos!$O$39/Supuestos!$Q$39 -> 0 | AH38: =AG38*Supuestos!$D$39*Supuestos!L$7 -> 0 | AI38: =IFERROR((AH38-AG38)/AG38,"-") -> - | AJ38: =Supuestos!$C$39*Supuestos!$P$39/Supuestos!$Q$39 -> 0 | AK38: =AJ38*Supuestos!$D$39*Supuestos!M$7 -> 0 | AL38: =IFERROR((AK38-AJ38)/AJ38,"-") -> - | AM38: =C38+F38+I38+L38+O38+R38+U38+X38+AA38+AD38+AG38+AJ38 -> 1500000 | AN38: =D38+G38+J38+M38+P38+S38+V38+Y38+AB38+AE38+AH38+AK38 -> 4725000 | AO38: =IFERROR((AN38-AM38)/AM38,"-") -> 2.15
A39: COMUNIDAD Y ALIANZAS | B39: Patrocinio torneo de fútbol amateur | C39: =Supuestos!$C$40*Supuestos!$E$40/Supuestos!$Q$40 -> 0 | D39: =C39*Supuestos!$D$40*Supuestos!B$7 -> 0 | E39: =IFERROR((D39-C39)/C39,"-") -> - | F39: =Supuestos!$C$40*Supuestos!$F$40/Supuestos!$Q$40 -> 0 | G39: =F39*Supuestos!$D$40*Supuestos!C$7 -> 0 | H39: =IFERROR((G39-F39)/F39,"-") -> - | I39: =Supuestos!$C$40*Supuestos!$G$40/Supuestos!$Q$40 -> 0 | J39: =I39*Supuestos!$D$40*Supuestos!D$7 -> 0 | K39: =IFERROR((J39-I39)/I39,"-") -> - | L39: =Supuestos!$C$40*Supuestos!$H$40/Supuestos!$Q$40 -> 0 | M39: =L39*Supuestos!$D$40*Supuestos!E$7 -> 0 | N39: =IFERROR((M39-L39)/L39,"-") -> - | O39: =Supuestos!$C$40*Supuestos!$I$40/Supuestos!$Q$40 -> 0 | P39: =O39*Supuestos!$D$40*Supuestos!F$7 -> 0 | Q39: =IFERROR((P39-O39)/O39,"-") -> - | R39: =Supuestos!$C$40*Supuestos!$J$40/Supuestos!$Q$40 -> 0 | S39: =R39*Supuestos!$D$40*Supuestos!G$7 -> 0 | T39: =IFERROR((S39-R39)/R39,"-") -> - | U39: =Supuestos!$C$40*Supuestos!$K$40/Supuestos!$Q$40 -> 0 | V39: =U39*Supuestos!$D$40*Supuestos!H$7 -> 0 | W39: =IFERROR((V39-U39)/U39,"-") -> - | X39: =Supuestos!$C$40*Supuestos!$L$40/Supuestos!$Q$40 -> 1250000 | Y39: =X39*Supuestos!$D$40*Supuestos!I$7 -> 3281250 | Z39: =IFERROR((Y39-X39)/X39,"-") -> 1.625 | AA39: =Supuestos!$C$40*Supuestos!$M$40/Supuestos!$Q$40 -> 1250000 | AB39: =AA39*Supuestos!$D$40*Supuestos!J$7 -> 3437500 | AC39: =IFERROR((AB39-AA39)/AA39,"-") -> 1.75 | AD39: =Supuestos!$C$40*Supuestos!$N$40/Supuestos!$Q$40 -> 0 | AE39: =AD39*Supuestos!$D$40*Supuestos!K$7 -> 0 | AF39: =IFERROR((AE39-AD39)/AD39,"-") -> - | AG39: =Supuestos!$C$40*Supuestos!$O$40/Supuestos!$Q$40 -> 0 | AH39: =AG39*Supuestos!$D$40*Supuestos!L$7 -> 0 | AI39: =IFERROR((AH39-AG39)/AG39,"-") -> - | AJ39: =Supuestos!$C$40*Supuestos!$P$40/Supuestos!$Q$40 -> 0 | AK39: =AJ39*Supuestos!$D$40*Supuestos!M$7 -> 0 | AL39: =IFERROR((AK39-AJ39)/AJ39,"-") -> - | AM39: =C39+F39+I39+L39+O39+R39+U39+X39+AA39+AD39+AG39+AJ39 -> 2500000 | AN39: =D39+G39+J39+M39+P39+S39+V39+Y39+AB39+AE39+AH39+AK39 -> 6718750 | AO39: =IFERROR((AN39-AM39)/AM39,"-") -> 1.6875
A40: COMUNIDAD Y ALIANZAS | B40: Donación comunitaria (1x10 al banco de alimentos) | C40: =Supuestos!$C$41*Supuestos!$E$41/Supuestos!$Q$41 -> 0 | D40: =C40*Supuestos!$D$41*Supuestos!B$7 -> 0 | E40: =IFERROR((D40-C40)/C40,"-") -> - | F40: =Supuestos!$C$41*Supuestos!$F$41/Supuestos!$Q$41 -> 0 | G40: =F40*Supuestos!$D$41*Supuestos!C$7 -> 0 | H40: =IFERROR((G40-F40)/F40,"-") -> - | I40: =Supuestos!$C$41*Supuestos!$G$41/Supuestos!$Q$41 -> 0 | J40: =I40*Supuestos!$D$41*Supuestos!D$7 -> 0 | K40: =IFERROR((J40-I40)/I40,"-") -> - | L40: =Supuestos!$C$41*Supuestos!$H$41/Supuestos!$Q$41 -> 0 | M40: =L40*Supuestos!$D$41*Supuestos!E$7 -> 0 | N40: =IFERROR((M40-L40)/L40,"-") -> - | O40: =Supuestos!$C$41*Supuestos!$I$41/Supuestos!$Q$41 -> 0 | P40: =O40*Supuestos!$D$41*Supuestos!F$7 -> 0 | Q40: =IFERROR((P40-O40)/O40,"-") -> - | R40: =Supuestos!$C$41*Supuestos!$J$41/Supuestos!$Q$41 -> 0 | S40: =R40*Supuestos!$D$41*Supuestos!G$7 -> 0 | T40: =IFERROR((S40-R40)/R40,"-") -> - | U40: =Supuestos!$C$41*Supuestos!$K$41/Supuestos!$Q$41 -> 0 | V40: =U40*Supuestos!$D$41*Supuestos!H$7 -> 0 | W40: =IFERROR((V40-U40)/U40,"-") -> - | X40: =Supuestos!$C$41*Supuestos!$L$41/Supuestos!$Q$41 -> 0 | Y40: =X40*Supuestos!$D$41*Supuestos!I$7 -> 0 | Z40: =IFERROR((Y40-X40)/X40,"-") -> - | AA40: =Supuestos!$C$41*Supuestos!$M$41/Supuestos!$Q$41 -> 0 | AB40: =AA40*Supuestos!$D$41*Supuestos!J$7 -> 0 | AC40: =IFERROR((AB40-AA40)/AA40,"-") -> - | AD40: =Supuestos!$C$41*Supuestos!$N$41/Supuestos!$Q$41 -> 900000 | AE40: =AD40*Supuestos!$D$41*Supuestos!K$7 -> 1782000 | AF40: =IFERROR((AE40-AD40)/AD40,"-") -> 0.98 | AG40: =Supuestos!$C$41*Supuestos!$O$41/Supuestos!$Q$41 -> 900000 | AH40: =AG40*Supuestos!$D$41*Supuestos!L$7 -> 1863000 | AI40: =IFERROR((AH40-AG40)/AG40,"-") -> 1.07 | AJ40: =Supuestos!$C$41*Supuestos!$P$41/Supuestos!$Q$41 -> 0 | AK40: =AJ40*Supuestos!$D$41*Supuestos!M$7 -> 0 | AL40: =IFERROR((AK40-AJ40)/AJ40,"-") -> - | AM40: =C40+F40+I40+L40+O40+R40+U40+X40+AA40+AD40+AG40+AJ40 -> 1800000 | AN40: =D40+G40+J40+M40+P40+S40+V40+Y40+AB40+AE40+AH40+AK40 -> 3645000 | AO40: =IFERROR((AN40-AM40)/AM40,"-") -> 1.025
A41: PRODUCTO Y MENÚ — Total | C41: =C42 -> 0 | D41: =D42 -> 0 | E41: =IFERROR((D41-C41)/C41,"-") -> - | F41: =F42 -> 0 | G41: =G42 -> 0 | H41: =IFERROR((G41-F41)/F41,"-") -> - | I41: =I42 -> 0 | J41: =J42 -> 0 | K41: =IFERROR((J41-I41)/I41,"-") -> - | L41: =L42 -> 0 | M41: =M42 -> 0 | N41: =IFERROR((M41-L41)/L41,"-") -> - | O41: =O42 -> 0 | P41: =P42 -> 0 | Q41: =IFERROR((P41-O41)/O41,"-") -> - | R41: =R42 -> 1000000 | S41: =S42 -> 2850000 | T41: =IFERROR((S41-R41)/R41,"-") -> 1.85 | U41: =U42 -> 1000000 | V41: =V42 -> 3000000 | W41: =IFERROR((V41-U41)/U41,"-") -> 2 | X41: =X42 -> 1000000 | Y41: =Y42 -> 3150000 | Z41: =IFERROR((Y41-X41)/X41,"-") -> 2.15 | AA41: =AA42 -> 0 | AB41: =AB42 -> 0 | AC41: =IFERROR((AB41-AA41)/AA41,"-") -> - | AD41: =AD42 -> 0 | AE41: =AE42 -> 0 | AF41: =IFERROR((AE41-AD41)/AD41,"-") -> - | AG41: =AG42 -> 0 | AH41: =AH42 -> 0 | AI41: =IFERROR((AH41-AG41)/AG41,"-") -> - | AJ41: =AJ42 -> 0 | AK41: =AK42 -> 0 | AL41: =IFERROR((AK41-AJ41)/AJ41,"-") -> - | AM41: =C41+F41+I41+L41+O41+R41+U41+X41+AA41+AD41+AG41+AJ41 -> 3000000 | AN41: =D41+G41+J41+M41+P41+S41+V41+Y41+AB41+AE41+AH41+AK41 -> 9000000 | AO41: =IFERROR((AN41-AM41)/AM41,"-") -> 2
A42: PRODUCTO Y MENÚ | B42: Encuesta + döner picante edición limitada | C42: =Supuestos!$C$42*Supuestos!$E$42/Supuestos!$Q$42 -> 0 | D42: =C42*Supuestos!$D$42*Supuestos!B$7 -> 0 | E42: =IFERROR((D42-C42)/C42,"-") -> - | F42: =Supuestos!$C$42*Supuestos!$F$42/Supuestos!$Q$42 -> 0 | G42: =F42*Supuestos!$D$42*Supuestos!C$7 -> 0 | H42: =IFERROR((G42-F42)/F42,"-") -> - | I42: =Supuestos!$C$42*Supuestos!$G$42/Supuestos!$Q$42 -> 0 | J42: =I42*Supuestos!$D$42*Supuestos!D$7 -> 0 | K42: =IFERROR((J42-I42)/I42,"-") -> - | L42: =Supuestos!$C$42*Supuestos!$H$42/Supuestos!$Q$42 -> 0 | M42: =L42*Supuestos!$D$42*Supuestos!E$7 -> 0 | N42: =IFERROR((M42-L42)/L42,"-") -> - | O42: =Supuestos!$C$42*Supuestos!$I$42/Supuestos!$Q$42 -> 0 | P42: =O42*Supuestos!$D$42*Supuestos!F$7 -> 0 | Q42: =IFERROR((P42-O42)/O42,"-") -> - | R42: =Supuestos!$C$42*Supuestos!$J$42/Supuestos!$Q$42 -> 1000000 | S42: =R42*Supuestos!$D$42*Supuestos!G$7 -> 2850000 | T42: =IFERROR((S42-R42)/R42,"-") -> 1.85 | U42: =Supuestos!$C$42*Supuestos!$K$42/Supuestos!$Q$42 -> 1000000 | V42: =U42*Supuestos!$D$42*Supuestos!H$7 -> 3000000 | W42: =IFERROR((V42-U42)/U42,"-") -> 2 | X42: =Supuestos!$C$42*Supuestos!$L$42/Supuestos!$Q$42 -> 1000000 | Y42: =X42*Supuestos!$D$42*Supuestos!I$7 -> 3150000 | Z42: =IFERROR((Y42-X42)/X42,"-") -> 2.15 | AA42: =Supuestos!$C$42*Supuestos!$M$42/Supuestos!$Q$42 -> 0 | AB42: =AA42*Supuestos!$D$42*Supuestos!J$7 -> 0 | AC42: =IFERROR((AB42-AA42)/AA42,"-") -> - | AD42: =Supuestos!$C$42*Supuestos!$N$42/Supuestos!$Q$42 -> 0 | AE42: =AD42*Supuestos!$D$42*Supuestos!K$7 -> 0 | AF42: =IFERROR((AE42-AD42)/AD42,"-") -> - | AG42: =Supuestos!$C$42*Supuestos!$O$42/Supuestos!$Q$42 -> 0 | AH42: =AG42*Supuestos!$D$42*Supuestos!L$7 -> 0 | AI42: =IFERROR((AH42-AG42)/AG42,"-") -> - | AJ42: =Supuestos!$C$42*Supuestos!$P$42/Supuestos!$Q$42 -> 0 | AK42: =AJ42*Supuestos!$D$42*Supuestos!M$7 -> 0 | AL42: =IFERROR((AK42-AJ42)/AJ42,"-") -> - | AM42: =C42+F42+I42+L42+O42+R42+U42+X42+AA42+AD42+AG42+AJ42 -> 3000000 | AN42: =D42+G42+J42+M42+P42+S42+V42+Y42+AB42+AE42+AH42+AK42 -> 9000000 | AO42: =IFERROR((AN42-AM42)/AM42,"-") -> 2
A43: TEMPORADA BAJA — Total | C43: =C44+C45 -> 0 | D43: =D44+D45 -> 0 | E43: =IFERROR((D43-C43)/C43,"-") -> - | F43: =F44+F45 -> 0 | G43: =G44+G45 -> 0 | H43: =IFERROR((G43-F43)/F43,"-") -> - | I43: =I44+I45 -> 750000 | J43: =J44+J45 -> 1485000 | K43: =IFERROR((J43-I43)/I43,"-") -> 0.98 | L43: =L44+L45 -> 750000 | M43: =M44+M45 -> 1402500 | N43: =IFERROR((M43-L43)/L43,"-") -> 0.87 | O43: =O44+O45 -> 0 | P43: =P44+P45 -> 0 | Q43: =IFERROR((P43-O43)/O43,"-") -> - | R43: =R44+R45 -> 900000 | S43: =S44+S45 -> 2052000 | T43: =IFERROR((S43-R43)/R43,"-") -> 1.28 | U43: =U44+U45 -> 900000 | V43: =V44+V45 -> 2160000 | W43: =IFERROR((V43-U43)/U43,"-") -> 1.4 | X43: =X44+X45 -> 0 | Y43: =Y44+Y45 -> 0 | Z43: =IFERROR((Y43-X43)/X43,"-") -> - | AA43: =AA44+AA45 -> 0 | AB43: =AB44+AB45 -> 0 | AC43: =IFERROR((AB43-AA43)/AA43,"-") -> - | AD43: =AD44+AD45 -> 0 | AE43: =AE44+AE45 -> 0 | AF43: =IFERROR((AE43-AD43)/AD43,"-") -> - | AG43: =AG44+AG45 -> 0 | AH43: =AH44+AH45 -> 0 | AI43: =IFERROR((AH43-AG43)/AG43,"-") -> - | AJ43: =AJ44+AJ45 -> 0 | AK43: =AK44+AK45 -> 0 | AL43: =IFERROR((AK43-AJ43)/AJ43,"-") -> - | AM43: =C43+F43+I43+L43+O43+R43+U43+X43+AA43+AD43+AG43+AJ43 -> 3300000 | AN43: =D43+G43+J43+M43+P43+S43+V43+Y43+AB43+AE43+AH43+AK43 -> 7099500 | AO43: =IFERROR((AN43-AM43)/AM43,"-") -> 1.1513636
A44: TEMPORADA BAJA | B44: Happy Hour entre semana (3-5pm) | C44: =Supuestos!$C$43*Supuestos!$E$43/Supuestos!$Q$43 -> 0 | D44: =C44*Supuestos!$D$43*Supuestos!B$7 -> 0 | E44: =IFERROR((D44-C44)/C44,"-") -> - | F44: =Supuestos!$C$43*Supuestos!$F$43/Supuestos!$Q$43 -> 0 | G44: =F44*Supuestos!$D$43*Supuestos!C$7 -> 0 | H44: =IFERROR((G44-F44)/F44,"-") -> - | I44: =Supuestos!$C$43*Supuestos!$G$43/Supuestos!$Q$43 -> 750000 | J44: =I44*Supuestos!$D$43*Supuestos!D$7 -> 1485000 | K44: =IFERROR((J44-I44)/I44,"-") -> 0.98 | L44: =Supuestos!$C$43*Supuestos!$H$43/Supuestos!$Q$43 -> 750000 | M44: =L44*Supuestos!$D$43*Supuestos!E$7 -> 1402500 | N44: =IFERROR((M44-L44)/L44,"-") -> 0.87 | O44: =Supuestos!$C$43*Supuestos!$I$43/Supuestos!$Q$43 -> 0 | P44: =O44*Supuestos!$D$43*Supuestos!F$7 -> 0 | Q44: =IFERROR((P44-O44)/O44,"-") -> - | R44: =Supuestos!$C$43*Supuestos!$J$43/Supuestos!$Q$43 -> 0 | S44: =R44*Supuestos!$D$43*Supuestos!G$7 -> 0 | T44: =IFERROR((S44-R44)/R44,"-") -> - | U44: =Supuestos!$C$43*Supuestos!$K$43/Supuestos!$Q$43 -> 0 | V44: =U44*Supuestos!$D$43*Supuestos!H$7 -> 0 | W44: =IFERROR((V44-U44)/U44,"-") -> - | X44: =Supuestos!$C$43*Supuestos!$L$43/Supuestos!$Q$43 -> 0 | Y44: =X44*Supuestos!$D$43*Supuestos!I$7 -> 0 | Z44: =IFERROR((Y44-X44)/X44,"-") -> - | AA44: =Supuestos!$C$43*Supuestos!$M$43/Supuestos!$Q$43 -> 0 | AB44: =AA44*Supuestos!$D$43*Supuestos!J$7 -> 0 | AC44: =IFERROR((AB44-AA44)/AA44,"-") -> - | AD44: =Supuestos!$C$43*Supuestos!$N$43/Supuestos!$Q$43 -> 0 | AE44: =AD44*Supuestos!$D$43*Supuestos!K$7 -> 0 | AF44: =IFERROR((AE44-AD44)/AD44,"-") -> - | AG44: =Supuestos!$C$43*Supuestos!$O$43/Supuestos!$Q$43 -> 0 | AH44: =AG44*Supuestos!$D$43*Supuestos!L$7 -> 0 | AI44: =IFERROR((AH44-AG44)/AG44,"-") -> - | AJ44: =Supuestos!$C$43*Supuestos!$P$43/Supuestos!$Q$43 -> 0 | AK44: =AJ44*Supuestos!$D$43*Supuestos!M$7 -> 0 | AL44: =IFERROR((AK44-AJ44)/AJ44,"-") -> - | AM44: =C44+F44+I44+L44+O44+R44+U44+X44+AA44+AD44+AG44+AJ44 -> 1500000 | AN44: =D44+G44+J44+M44+P44+S44+V44+Y44+AB44+AE44+AH44+AK44 -> 2887500 | AO44: =IFERROR((AN44-AM44)/AM44,"-") -> 0.925
A45: TEMPORADA BAJA | B45: Envío gratis vacaciones de mitad de año | C45: =Supuestos!$C$44*Supuestos!$E$44/Supuestos!$Q$44 -> 0 | D45: =C45*Supuestos!$D$44*Supuestos!B$7 -> 0 | E45: =IFERROR((D45-C45)/C45,"-") -> - | F45: =Supuestos!$C$44*Supuestos!$F$44/Supuestos!$Q$44 -> 0 | G45: =F45*Supuestos!$D$44*Supuestos!C$7 -> 0 | H45: =IFERROR((G45-F45)/F45,"-") -> - | I45: =Supuestos!$C$44*Supuestos!$G$44/Supuestos!$Q$44 -> 0 | J45: =I45*Supuestos!$D$44*Supuestos!D$7 -> 0 | K45: =IFERROR((J45-I45)/I45,"-") -> - | L45: =Supuestos!$C$44*Supuestos!$H$44/Supuestos!$Q$44 -> 0 | M45: =L45*Supuestos!$D$44*Supuestos!E$7 -> 0 | N45: =IFERROR((M45-L45)/L45,"-") -> - | O45: =Supuestos!$C$44*Supuestos!$I$44/Supuestos!$Q$44 -> 0 | P45: =O45*Supuestos!$D$44*Supuestos!F$7 -> 0 | Q45: =IFERROR((P45-O45)/O45,"-") -> - | R45: =Supuestos!$C$44*Supuestos!$J$44/Supuestos!$Q$44 -> 900000 | S45: =R45*Supuestos!$D$44*Supuestos!G$7 -> 2052000 | T45: =IFERROR((S45-R45)/R45,"-") -> 1.28 | U45: =Supuestos!$C$44*Supuestos!$K$44/Supuestos!$Q$44 -> 900000 | V45: =U45*Supuestos!$D$44*Supuestos!H$7 -> 2160000 | W45: =IFERROR((V45-U45)/U45,"-") -> 1.4 | X45: =Supuestos!$C$44*Supuestos!$L$44/Supuestos!$Q$44 -> 0 | Y45: =X45*Supuestos!$D$44*Supuestos!I$7 -> 0 | Z45: =IFERROR((Y45-X45)/X45,"-") -> - | AA45: =Supuestos!$C$44*Supuestos!$M$44/Supuestos!$Q$44 -> 0 | AB45: =AA45*Supuestos!$D$44*Supuestos!J$7 -> 0 | AC45: =IFERROR((AB45-AA45)/AA45,"-") -> - | AD45: =Supuestos!$C$44*Supuestos!$N$44/Supuestos!$Q$44 -> 0 | AE45: =AD45*Supuestos!$D$44*Supuestos!K$7 -> 0 | AF45: =IFERROR((AE45-AD45)/AD45,"-") -> - | AG45: =Supuestos!$C$44*Supuestos!$O$44/Supuestos!$Q$44 -> 0 | AH45: =AG45*Supuestos!$D$44*Supuestos!L$7 -> 0 | AI45: =IFERROR((AH45-AG45)/AG45,"-") -> - | AJ45: =Supuestos!$C$44*Supuestos!$P$44/Supuestos!$Q$44 -> 0 | AK45: =AJ45*Supuestos!$D$44*Supuestos!M$7 -> 0 | AL45: =IFERROR((AK45-AJ45)/AJ45,"-") -> - | AM45: =C45+F45+I45+L45+O45+R45+U45+X45+AA45+AD45+AG45+AJ45 -> 1800000 | AN45: =D45+G45+J45+M45+P45+S45+V45+Y45+AB45+AE45+AH45+AK45 -> 4212000 | AO45: =IFERROR((AN45-AM45)/AM45,"-") -> 1.34
A47: TOTAL MEDIA INVESTMENT | C47: =C6+C9+C17+C25+C35+C41+C43 -> 10100000 | F47: =F6+F9+F17+F25+F35+F41+F43 -> 17159091 | I47: =I6+I9+I17+I25+I35+I41+I43 -> 11209091 | L47: =L6+L9+L17+L25+L35+L41+L43 -> 10209091 | O47: =O6+O9+O17+O25+O35+O41+O43 -> 13459091 | R47: =R6+R9+R17+R25+R35+R41+R43 -> 11109091 | U47: =U6+U9+U17+U25+U35+U41+U43 -> 11109091 | X47: =X6+X9+X17+X25+X35+X41+X43 -> 14209091 | AA47: =AA6+AA9+AA17+AA25+AA35+AA41+AA43 -> 12159091 | AD47: =AD6+AD9+AD17+AD25+AD35+AD41+AD43 -> 13009091 | AG47: =AG6+AG9+AG17+AG25+AG35+AG41+AG43 -> 11759091 | AJ47: =AJ6+AJ9+AJ17+AJ25+AJ35+AJ41+AJ43 -> 10209091 | AM47: =AM6+AM9+AM17+AM25+AM35+AM41+AM43 -> 145700000
A48: TOTAL NET REVENUE (P&L) | D48: =D6+D9+D17+D25+D35+D41+D43 -> 37320000 | G48: =G6+G9+G17+G25+G35+G41+G43 -> 67301136 | J48: =J6+J9+J17+J25+J35+J41+J43 -> 34832455 | M48: =M6+M9+M17+M25+M35+M41+M43 -> 30984818 | P48: =P6+P9+P17+P25+P35+P41+P43 -> 51242864 | S48: =S6+S9+S17+S25+S35+S41+S43 -> 38582091 | V48: =V6+V9+V17+V25+V35+V41+V43 -> 40412727 | Y48: =Y6+Y9+Y17+Y25+Y35+Y41+Y43 -> 50901614 | AB48: =AB6+AB9+AB17+AB25+AB35+AB41+AB43 -> 48155500 | AE48: =AE6+AE9+AE17+AE25+AE35+AE41+AE43 -> 48194000 | AH48: =AH6+AH9+AH17+AH25+AH35+AH41+AH43 -> 49119636 | AK48: =AK6+AK9+AK17+AK25+AK35+AK41+AK43 -> 56553545 | AN48: =AN6+AN9+AN17+AN25+AN35+AN41+AN43 -> 5.5360039e+08
A49: % REVENUE vs INVESTMENT | E49: =IFERROR((D48-C47)/C47,"-") -> 2.6950495 | H49: =IFERROR((G48-F47)/F47,"-") -> 2.9221854 | K49: =IFERROR((J48-I47)/I47,"-") -> 2.1075182 | N49: =IFERROR((M48-L47)/L47,"-") -> 2.0350223 | Q49: =IFERROR((P48-O47)/O47,"-") -> 2.807305 | T49: =IFERROR((S48-R47)/R47,"-") -> 2.4730196 | W49: =IFERROR((V48-U47)/U47,"-") -> 2.6378069 | Z49: =IFERROR((Y48-X47)/X47,"-") -> 2.5823273 | AC49: =IFERROR((AB48-AA47)/AA47,"-") -> 2.9604523 | AF49: =IFERROR((AE48-AD47)/AD47,"-") -> 2.7046401 | AI49: =IFERROR((AH48-AG47)/AG47,"-") -> 3.1771627 | AL49: =IFERROR((AK48-AJ47)/AJ47,"-") -> 4.539528 | AO49: =IFERROR((AN48-AM47)/AM47,"-") -> 2.7995908
A50: ROI ESTIMADO | E50: =IFERROR(D48/C47,"-") -> 3.6950495 | H50: =IFERROR(G48/F47,"-") -> 3.9221854 | K50: =IFERROR(J48/I47,"-") -> 3.1075182 | N50: =IFERROR(M48/L47,"-") -> 3.0350223 | Q50: =IFERROR(P48/O47,"-") -> 3.807305 | T50: =IFERROR(S48/R47,"-") -> 3.4730196 | W50: =IFERROR(V48/U47,"-") -> 3.6378069 | Z50: =IFERROR(Y48/X47,"-") -> 3.5823273 | AC50: =IFERROR(AB48/AA47,"-") -> 3.9604523 | AF50: =IFERROR(AE48/AD47,"-") -> 3.7046401 | AI50: =IFERROR(AH48/AG47,"-") -> 4.1771627 | AL50: =IFERROR(AK48/AJ47,"-") -> 5.539528 | AO50: =IFERROR(AN48/AM47,"-") -> 3.7995908

Sheet Supuestos
A1: SUPUESTOS Y PRESUPUESTO DE MARKETING — DÖNER HOUSE 2027
A3: Ticket promedio (COP): | B3: 27000 | C3: Supuesto propio: precio promedio de un Combo Döner individual en el mercado de Bogotá (rango observado COP 22.000-32.000).
A5: Índice de estacionalidad mensual (multiplicador de demanda esperado)
A6: Mes | B6: Ene | C6: Feb | D6: Mar | E6: Abr | F6: May | G6: Jun | H6: Jul | I6: Ago | J6: Sep | K6: Oct | L6: Nov | M6: Dic
A7: Índice | B7: 1.2 | C7: 1.15 | D7: 0.9 | E7: 0.85 | F7: 1.05 | G7: 0.95 | H7: 1 | I7: 1.05 | J7: 1.1 | K7: 1.1 | L7: 1.15 | M7: 1.3
A8: Justificación | B8: Ene: apertura; Feb: San Valentín + bienvenida universitaria; Mar-Abr: temporada baja; May: Día de la Madre; Jun: Día del Padre / receso escolar; Jul: aniversario; Ago: bienvenida 2 + torneo; Sep: Amor y Amistad; Oct: puente/Halloween/lluvias; Nov: puente + Black Friday; Dic: Navidad y fin de año.
A10: Presupuesto y supuestos por canal (según el Plan de Campañas 2027)
A11: Área | B11: Canal | C11: Presupuesto Anual (COP) | D11: ROAS esperado (x) | E11: Ene | F11: Feb | G11: Mar | H11: Abr | I11: May | J11: Jun | K11: Jul | L11: Ago | M11: Sep | N11: Oct | O11: Nov | P11: Dic | Q11: Meses Activos | R11: Justificación / fuente (Plan de Campañas)
A12: LANZAMIENTO | B12: Prensa y Redes (Teaser + PR + Promo apertura) | C12: 3000000 | D12: 3 | E12: 1 | F12: 0 | G12: 0 | H12: 0 | I12: 0 | J12: 0 | K12: 0 | L12: 0 | M12: 0 | N12: 0 | O12: 0 | P12: 0 | Q12: =SUM(E12:P12) -> 1 | R12: Teaser IG/TikTok, prensa local y semana de apertura (Plan: 4-25 ene)
A13: LANZAMIENTO | B13: Volantes, degustaciones y garantía de satisfacción | C13: 2000000 | D13: 3.5 | E13: 1 | F13: 1 | G13: 0 | H13: 0 | I13: 0 | J13: 0 | K13: 0 | L13: 0 | M13: 0 | N13: 0 | O13: 0 | P13: 0 | Q13: =SUM(E13:P13) -> 2 | R13: Flyers en oficinas/universidades y señalización de garantía (Plan: 18 ene-1 feb)
A14: PUBLICIDAD DIGITAL | B14: Contenido orgánico IG/TikTok/Facebook | C14: 12000000 | D14: 2.5 | E14: 1 | F14: 1 | G14: 1 | H14: 1 | I14: 1 | J14: 1 | K14: 1 | L14: 1 | M14: 1 | N14: 1 | O14: 1 | P14: 1 | Q14: =SUM(E14:P14) -> 12 | R14: Always-on todo el año (Plan: 4 ene-31 dic)
A15: PUBLICIDAD DIGITAL | B15: Google Business Profile (SEO local) | C15: 1200000 | D15: 6 | E15: 1 | F15: 1 | G15: 1 | H15: 1 | I15: 1 | J15: 1 | K15: 1 | L15: 1 | M15: 1 | N15: 1 | O15: 1 | P15: 1 | Q15: =SUM(E15:P15) -> 12 | R15: Fotos, horarios, menú y reseñas todo el año; costo bajo, alta intención de compra
A16: PUBLICIDAD DIGITAL | B16: Meta Ads pagado (geo-segmentado) | C16: 24000000 | D16: 4 | E16: 1 | F16: 1 | G16: 1 | H16: 1 | I16: 1 | J16: 1 | K16: 1 | L16: 1 | M16: 1 | N16: 1 | O16: 1 | P16: 1 | Q16: =SUM(E16:P16) -> 12 | R16: Radio alrededor de la tienda (Plan: 18 ene-31 dic)
A17: PUBLICIDAD DIGITAL | B17: Influencers y bloggers gastronómicos | C17: 6000000 | D17: 3.2 | E17: 0 | F17: 1 | G17: 0 | H17: 0 | I17: 0 | J17: 0 | K17: 0 | L17: 1 | M17: 0 | N17: 0 | O17: 0 | P17: 0 | Q17: =SUM(E17:P17) -> 2 | R17: Ola 1 (feb) y ola 2 (ago) de colaboraciones en Bogotá
A18: PUBLICIDAD DIGITAL | B18: QR en empaques/recibos + referidos | C18: 8000000 | D18: 5 | E18: 0 | F18: 1 | G18: 1 | H18: 1 | I18: 1 | J18: 1 | K18: 1 | L18: 1 | M18: 1 | N18: 1 | O18: 1 | P18: 1 | Q18: =SUM(E18:P18) -> 11 | R18: QR con 10% dcto próxima compra (Plan: 15 feb-31 dic)
A19: PUBLICIDAD DIGITAL | B19: WhatsApp Business (catálogo + broadcast) | C19: 2400000 | D19: 4.5 | E19: 0 | F19: 1 | G19: 1 | H19: 1 | I19: 1 | J19: 1 | K19: 1 | L19: 1 | M19: 1 | N19: 1 | O19: 1 | P19: 1 | Q19: =SUM(E19:P19) -> 11 | R19: Catálogo y oferta semanal (Plan: 22 feb-31 dic)
A20: PUBLICIDAD DIGITAL | B20: Reto TikTok "el wrap perfecto" | C20: 1500000 | D20: 2.8 | E20: 0 | F20: 0 | G20: 0 | H20: 0 | I20: 0 | J20: 0 | K20: 0 | L20: 0 | M20: 1 | N20: 1 | O20: 0 | P20: 0 | Q20: =SUM(E20:P20) -> 2 | R20: Reto con premio (Plan: 27 sep-18 oct)
A21: DELIVERY Y FIDELIZACIÓN | B21: Lanzamiento apps delivery (dcto. introductorio) | C21: 6000000 | D21: 2.5 | E21: 1 | F21: 1 | G21: 0 | H21: 0 | I21: 0 | J21: 0 | K21: 0 | L21: 0 | M21: 0 | N21: 0 | O21: 0 | P21: 0 | Q21: =SUM(E21:P21) -> 2 | R21: Rappi, Uber Eats y DiDi Food con descuento de lanzamiento (Plan: 25 ene-22 feb)
A22: DELIVERY Y FIDELIZACIÓN | B22: Tarjeta de lealtad (10º döner gratis) | C22: 15000000 | D22: 4 | E22: 0 | F22: 1 | G22: 1 | H22: 1 | I22: 1 | J22: 1 | K22: 1 | L22: 1 | M22: 1 | N22: 1 | O22: 1 | P22: 1 | Q22: =SUM(E22:P22) -> 11 | R22: Costo del beneficio de fidelización (Plan: 1 feb-31 dic)
A23: DELIVERY Y FIDELIZACIÓN | B23: Descuento estudiantes/oficinistas (10%) | C23: 10000000 | D23: 3 | E23: 0 | F23: 1 | G23: 1 | H23: 1 | I23: 1 | J23: 0 | K23: 0 | L23: 1 | M23: 1 | N23: 1 | O23: 1 | P23: 0 | Q23: =SUM(E23:P23) -> 8 | R23: Semestre 1 (feb-may) y semestre 2 (ago-nov)
... A44: TEMPORADA BAJA | B44: Envío gratis vacaciones de mitad de año | C44: 1800000 | D44: 2.4 | E44: 0 | F44: 0 | G44: 0 | H44: 0 | I44: 0 | J44: 1 | K44: 1 | L44: 0 | M44: 0 | N44: 0 | O44: 0 | P44: 0 | Q44: =SUM(E44:P44) -> 2 | R44: Pedidos > $40.000 (Plan: 21 jun-12 jul)
A45: TOTAL | B45: Presupuesto anual de marketing | C45: =SUM(C12:C44) -> 145700000
